{
  "pagination": {
    "_limit": 20,
    "_prev": null,
    "_next": null
  },
  "data": [
    {
      "teamMetadata": {
        "name": "Manchester United",
        "season": "2025",
        "id": "1",
        "shortName": "Man Utd",
        "abbr": "MUN"
      },
      "stats": {
        "duelsLost": 1476.0,
        "blockedShots": 121.0,
        "shotsOnTargetIncGoals": 167.0,
        "expectedGoalsOnTarget": 43.3441,
        "gamesPlayed": 29.0,
        "setPiecesGoals": 1.0,
        "crossingAccuracy": 28.37,
        "totalPasses": 13726.0,
        "goals": 51.0,
        "offsides": 46.0,
        "awayGoals": 24.0,
        "tackleSuccess": 58.52,
        "redCard2ndYellow": 1.0,
        "oboxBlocked": 49.0,
        "passingAccuracy": 82.86,
        "iboxTarget": 73.0,
        "aerialDuelsLost": 512.0,
        "goalsConcededOutsideBox": 4.0,
        "ownGoalsAccrued": 2.0,
        "groundDuelsWon": 1023.0,
        "successfulCornersIntoBox": 38.0,
        "penaltyGoalsConceded": 3.0,
        "expectedGoalsOnTargetConceded": 42.9769,
        "keyPassesAttemptAssists": 310.0,
        "successfulLaunches": 132.0,
        "totalFoulsWon": 309.0,
        "recoveries": 1397.0,
        "pointsGainedFromLosingPositions": 15.0,
        "passingPercentOppHalf": 77.68,
        "shotsOnConcededInsideBox": 84.0,
        "rightFootGoals": 27.0,
        "leftFootGoals": 12.0,
        "unsuccessfulDribbles": 221.0,
        "unsuccessfulCrossesAndCorners": 356.0,
        "timesTackled": 471.0,
        "freekickTotal": 6.0,
        "openPlayPasses": 13085.0,
        "gkSuccessfulDistribution": 200.0,
        "shotsOffTargetIncWoodwork": 174.0,
        "totalLossesOfPossession": 3831.0,
        "tacklesWon": 309.0,
        "attemptsFromSetPieces": 6.0,
        "totalShotsConceded": 316.0,
        "totalFoulsConceded": 298.0,
        "unsuccessfulCornersIntoBox": 76.0,
        "successfulLongPasses": 652.0,
        "clearancesOffTheLine": 2.0,
        "throwInsToOwnPlayer": 426.0,
        "touchesInOppBox": 805.0,
        "hitWoodwork": 18.0,
        "successfulPassesOwnHalf": 5370.0,
        "pointsDroppedFromWinningPositions": 14.0,
        "ownGoalsConceded": 2.0,
        "handballsConceded": 8.0,
        "unsuccessfulLongPasses": 802.0,
        "unsuccessfulPassesOwnHalf": 628.0,
        "successfulCrossesOpenPlay": 96.0,
        "expectedAssists": 31.4471,
        "totalRedCards": 1.0,
        "expectedGoalsFreekick": 0.5647,
        "catches": 25.0,
        "overruns": 28.0,
        "unsuccessfulPassesOppositionHalf": 2081.0,
        "totalShots": 341.0,
        "unsuccessfulShortPasses": 1551.0,
        "goalAssists": 36.0,
        "successfulLayoffs": 315.0,
        "foulWonPenalty": 5.0,
        "unsuccessfulCrossesOpenPlay": 258.0,
        "goalKicks": 198.0,
        "cornersTakenInclShortCorners": 128.0,
        "aerialDuels": 1008.0,
        "cleanSheets": 5.0,
        "shootingAccuracy": 48.97,
        "successfulCrossesAndCorners": 141.0,
        "unsuccessfulLayoffs": 31.0,
        "duelsWon": 1519.0,
        "penaltiesConceded": 3.0,
        "putthroughBlockedDistribution": 477.0,
        "successfulShortPasses": 10721.0,
        "throwInsToOppositionPlayer": 117.0,
        "successfulOpenPlayPasses": 10897.0,
        "totalClearances": 706.0,
        "goalsConceded": 40.0,
        "groundDuelsLost": 964.0,
        "duels": 2995.0,
        "putthroughBlockedDistributionWon": 220.0,
        "homeGoals": 27.0,
        "possessionPercentage": 53.2,
        "oboxTarget": 45.0,
        "drops": 4.0,
        "tacklesLost": 219.0,
        "lastPlayerTackle": 5.0,
        "successfulPassesOppositionHalf": 6144.0,
        "goalsConcededInsideBox": 36.0,
        "headedGoals": 10.0,
        "iboxBlocked": 72.0,
        "groundDuels": 1987.0,
        "aerialDuelsWon": 496.0,
        "straightRedCards": 0.0,
        "cornersWon": 128.0,
        "successfulDribbles": 192.0,
        "blocks": 92.0,
        "gkUnsuccessfulDistribution": 67.0,
        "interceptions": 225.0,
        "penaltyGoals": 3.0,
        "unsuccessfulLaunches": 399.0,
        "foulAttemptedTackle": 173.0,
        "shotsOnConcededOutsideBox": 24.0,
        "goalConversion": 14.96,
        "expectedGoals": 50.3725,
        "yellowCards": 41.0
      }
    },
    {
      "teamMetadata": {
        "name": "Everton",
        "season": "2025",
        "id": "11",
        "shortName": "Everton",
        "abbr": "EVE"
      },
      "stats": {
        "duelsLost": 1517.0,
        "penaltiesSaved": 1.0,
        "blockedShots": 100.0,
        "shotsOnTargetIncGoals": 99.0,
        "expectedGoalsOnTarget": 31.9344,
        "gamesPlayed": 29.0,
        "crossingAccuracy": 22.1,
        "totalPasses": 11224.0,
        "goals": 34.0,
        "offsides": 38.0,
        "awayGoals": 16.0,
        "tackleSuccess": 58.33,
        "redCard2ndYellow": 1.0,
        "oboxBlocked": 35.0,
        "passingAccuracy": 79.81,
        "iboxTarget": 47.0,
        "aerialDuelsLost": 530.0,
        "goalsConcededOutsideBox": 3.0,
        "ownGoalsAccrued": 2.0,
        "groundDuelsWon": 1043.0,
        "successfulCornersIntoBox": 24.0,
        "penaltyGoalsConceded": 2.0,
        "expectedGoalsOnTargetConceded": 36.8265,
        "keyPassesAttemptAssists": 211.0,
        "successfulLaunches": 151.0,
        "totalFoulsWon": 330.0,
        "recoveries": 1402.0,
        "pointsGainedFromLosingPositions": 8.0,
        "passingPercentOppHalf": 73.44,
        "shotsOnConcededInsideBox": 89.0,
        "rightFootGoals": 14.0,
        "leftFootGoals": 10.0,
        "unsuccessfulDribbles": 263.0,
        "unsuccessfulCrossesAndCorners": 409.0,
        "otherGoals": 2.0,
        "timesTackled": 524.0,
        "freekickTotal": 10.0,
        "openPlayPasses": 10570.0,
        "gkSuccessfulDistribution": 257.0,
        "shotsOffTargetIncWoodwork": 122.0,
        "totalLossesOfPossession": 3927.0,
        "tacklesWon": 308.0,
        "attemptsFromSetPieces": 10.0,
        "totalShotsConceded": 385.0,
        "totalFoulsConceded": 307.0,
        "unsuccessfulCornersIntoBox": 89.0,
        "successfulLongPasses": 644.0,
        "clearancesOffTheLine": 7.0,
        "throwInsToOwnPlayer": 378.0,
        "touchesInOppBox": 694.0,
        "hitWoodwork": 14.0,
        "successfulPassesOwnHalf": 4170.0,
        "pointsDroppedFromWinningPositions": 9.0,
        "ownGoalsConceded": 1.0,
        "handballsConceded": 15.0,
        "unsuccessfulLongPasses": 898.0,
        "unsuccessfulPassesOwnHalf": 534.0,
        "successfulCrossesOpenPlay": 75.0,
        "expectedAssists": 24.9186,
        "totalRedCards": 4.0,
        "expectedGoalsFreekick": 0.3705,
        "catches": 10.0,
        "overruns": 21.0,
        "unsuccessfulPassesOppositionHalf": 2141.0,
        "totalShots": 221.0,
        "unsuccessfulShortPasses": 1368.0,
        "goalAssists": 25.0,
        "successfulLayoffs": 209.0,
        "foulWonPenalty": 2.0,
        "unsuccessfulCrossesOpenPlay": 284.0,
        "goalKicks": 224.0,
        "cornersTakenInclShortCorners": 129.0,
        "aerialDuels": 1184.0,
        "cleanSheets": 10.0,
        "shootingAccuracy": 44.8,
        "successfulCrossesAndCorners": 116.0,
        "unsuccessfulLayoffs": 28.0,
        "duelsWon": 1697.0,
        "penaltiesConceded": 3.0,
        "putthroughBlockedDistribution": 475.0,
        "successfulShortPasses": 8314.0,
        "throwInsToOppositionPlayer": 177.0,
        "successfulOpenPlayPasses": 8497.0,
        "totalClearances": 868.0,
        "goalsConceded": 33.0,
        "groundDuelsLost": 987.0,
        "duels": 3214.0,
        "putthroughBlockedDistributionWon": 234.0,
        "homeGoals": 18.0,
        "possessionPercentage": 44.2,
        "oboxTarget": 20.0,
        "drops": 2.0,
        "tacklesLost": 220.0,
        "lastPlayerTackle": 11.0,
        "successfulPassesOppositionHalf": 4904.0,
        "goalsConcededInsideBox": 30.0,
        "headedGoals": 6.0,
        "iboxBlocked": 65.0,
        "groundDuels": 2030.0,
        "aerialDuelsWon": 654.0,
        "straightRedCards": 3.0,
        "cornersWon": 129.0,
        "successfulDribbles": 191.0,
        "blocks": 122.0,
        "gkUnsuccessfulDistribution": 71.0,
        "interceptions": 241.0,
        "penaltyGoals": 2.0,
        "unsuccessfulLaunches": 483.0,
        "foulAttemptedTackle": 151.0,
        "shotsOnConcededOutsideBox": 29.0,
        "goalConversion": 15.38,
        "expectedGoals": 34.9242,
        "yellowCards": 53.0
      }
    },
    {
      "teamMetadata": {
        "name": "Liverpool",
        "season": "2025",
        "id": "14",
        "shortName": "Liverpool",
        "abbr": "LIV"
      },
      "stats": {
        "duelsLost": 1289.0,
        "penaltiesSaved": 1.0,
        "blockedShots": 153.0,
        "shotsOnTargetIncGoals": 131.0,
        "expectedGoalsOnTarget": 42.9141,
        "gamesPlayed": 29.0,
        "setPiecesGoals": 3.0,
        "crossingAccuracy": 21.25,
        "totalPasses": 15694.0,
        "goals": 48.0,
        "offsides": 61.0,
        "awayGoals": 22.0,
        "tackleSuccess": 62.56,
        "oboxBlocked": 67.0,
        "passingAccuracy": 85.99,
        "iboxTarget": 52.0,
        "aerialDuelsLost": 382.0,
        "goalsConcededOutsideBox": 7.0,
        "ownGoalsAccrued": 2.0,
        "groundDuelsWon": 916.0,
        "successfulCornersIntoBox": 45.0,
        "penaltyGoalsConceded": 3.0,
        "expectedGoalsOnTargetConceded": 33.1499,
        "keyPassesAttemptAssists": 325.0,
        "successfulLaunches": 88.0,
        "totalFoulsWon": 294.0,
        "recoveries": 1308.0,
        "pointsGainedFromLosingPositions": 5.0,
        "passingPercentOppHalf": 82.61,
        "shotsOnConcededInsideBox": 72.0,
        "rightFootGoals": 34.0,
        "leftFootGoals": 7.0,
        "unsuccessfulDribbles": 232.0,
        "unsuccessfulCrossesAndCorners": 478.0,
        "otherGoals": 1.0,
        "timesTackled": 468.0,
        "freekickTotal": 13.0,
        "openPlayPasses": 15070.0,
        "gkSuccessfulDistribution": 303.0,
        "shotsOffTargetIncWoodwork": 174.0,
        "totalLossesOfPossession": 3777.0,
        "tacklesWon": 244.0,
        "attemptsFromSetPieces": 13.0,
        "totalShotsConceded": 314.0,
        "totalFoulsConceded": 286.0,
        "unsuccessfulCornersIntoBox": 110.0,
        "successfulLongPasses": 611.0,
        "clearancesOffTheLine": 1.0,
        "throwInsToOwnPlayer": 499.0,
        "touchesInOppBox": 986.0,
        "hitWoodwork": 13.0,
        "successfulPassesOwnHalf": 5664.0,
        "pointsDroppedFromWinningPositions": 9.0,
        "handballsConceded": 7.0,
        "unsuccessfulLongPasses": 707.0,
        "unsuccessfulPassesOwnHalf": 551.0,
        "successfulCrossesOpenPlay": 70.0,
        "expectedAssists": 33.3535,
        "totalRedCards": 1.0,
        "expectedGoalsFreekick": 0.7135,
        "catches": 18.0,
        "overruns": 30.0,
        "unsuccessfulPassesOppositionHalf": 2126.0,
        "totalShots": 305.0,
        "unsuccessfulShortPasses": 1492.0,
        "goalAssists": 32.0,
        "successfulLayoffs": 275.0,
        "foulWonPenalty": 2.0,
        "unsuccessfulCrossesOpenPlay": 351.0,
        "goalKicks": 200.0,
        "cornersTakenInclShortCorners": 174.0,
        "aerialDuels": 848.0,
        "cleanSheets": 9.0,
        "shootingAccuracy": 42.95,
        "successfulCrossesAndCorners": 129.0,
        "unsuccessfulLayoffs": 17.0,
        "duelsWon": 1382.0,
        "penaltiesConceded": 4.0,
        "putthroughBlockedDistribution": 468.0,
        "successfulShortPasses": 12884.0,
        "throwInsToOppositionPlayer": 65.0,
        "successfulOpenPlayPasses": 12964.0,
        "totalClearances": 768.0,
        "goalsConceded": 39.0,
        "groundDuelsLost": 907.0,
        "duels": 2671.0,
        "putthroughBlockedDistributionWon": 202.0,
        "homeGoals": 26.0,
        "possessionPercentage": 60.0,
        "oboxTarget": 33.0,
        "drops": 3.0,
        "tacklesLost": 146.0,
        "lastPlayerTackle": 6.0,
        "successfulPassesOppositionHalf": 7960.0,
        "goalsConcededInsideBox": 32.0,
        "headedGoals": 4.0,
        "iboxBlocked": 86.0,
        "groundDuels": 1823.0,
        "aerialDuelsWon": 466.0,
        "straightRedCards": 1.0,
        "cornersWon": 174.0,
        "successfulDribbles": 236.0,
        "blocks": 87.0,
        "gkUnsuccessfulDistribution": 39.0,
        "interceptions": 189.0,
        "penaltyGoals": 1.0,
        "unsuccessfulLaunches": 320.0,
        "foulAttemptedTackle": 121.0,
        "shotsOnConcededOutsideBox": 32.0,
        "goalConversion": 15.74,
        "expectedGoals": 48.341,
        "yellowCards": 44.0
      }
    },
    {
      "teamMetadata": {
        "name": "Nottingham Forest",
        "season": "2025",
        "id": "17",
        "shortName": "Nott'm Forest",
        "abbr": "NFO"
      },
      "stats": {
        "duelsLost": 1458.0,
        "blockedShots": 122.0,
        "shotsOnTargetIncGoals": 114.0,
        "expectedGoalsOnTarget": 32.019,
        "gamesPlayed": 29.0,
        "crossingAccuracy": 20.12,
        "totalPasses": 12077.0,
        "goals": 28.0,
        "offsides": 47.0,
        "awayGoals": 15.0,
        "tackleSuccess": 60.53,
        "oboxBlocked": 56.0,
        "passingAccuracy": 82.68,
        "iboxTarget": 54.0,
        "aerialDuelsLost": 474.0,
        "goalsConcededOutsideBox": 9.0,
        "groundDuelsWon": 1022.0,
        "successfulCornersIntoBox": 33.0,
        "penaltyGoalsConceded": 5.0,
        "expectedGoalsOnTargetConceded": 38.6995,
        "keyPassesAttemptAssists": 251.0,
        "successfulLaunches": 162.0,
        "totalFoulsWon": 327.0,
        "recoveries": 1383.0,
        "pointsGainedFromLosingPositions": 9.0,
        "passingPercentOppHalf": 76.99,
        "shotsOnConcededInsideBox": 95.0,
        "rightFootGoals": 17.0,
        "leftFootGoals": 5.0,
        "unsuccessfulDribbles": 235.0,
        "unsuccessfulCrossesAndCorners": 552.0,
        "timesTackled": 486.0,
        "freekickTotal": 10.0,
        "openPlayPasses": 11409.0,
        "gkSuccessfulDistribution": 239.0,
        "shotsOffTargetIncWoodwork": 137.0,
        "totalLossesOfPossession": 3819.0,
        "tacklesWon": 296.0,
        "attemptsFromSetPieces": 10.0,
        "totalShotsConceded": 373.0,
        "totalFoulsConceded": 306.0,
        "unsuccessfulCornersIntoBox": 101.0,
        "successfulLongPasses": 653.0,
        "clearancesOffTheLine": 5.0,
        "throwInsToOwnPlayer": 415.0,
        "touchesInOppBox": 646.0,
        "hitWoodwork": 5.0,
        "successfulPassesOwnHalf": 4791.0,
        "pointsDroppedFromWinningPositions": 6.0,
        "ownGoalsConceded": 2.0,
        "handballsConceded": 16.0,
        "unsuccessfulLongPasses": 834.0,
        "unsuccessfulPassesOwnHalf": 540.0,
        "successfulCrossesOpenPlay": 103.0,
        "expectedAssists": 23.3171,
        "totalRedCards": 1.0,
        "expectedGoalsFreekick": 0.5241,
        "catches": 14.0,
        "overruns": 32.0,
        "unsuccessfulPassesOppositionHalf": 2104.0,
        "totalShots": 251.0,
        "unsuccessfulShortPasses": 1258.0,
        "goalAssists": 18.0,
        "successfulLayoffs": 220.0,
        "foulWonPenalty": 2.0,
        "unsuccessfulCrossesOpenPlay": 425.0,
        "goalKicks": 231.0,
        "cornersTakenInclShortCorners": 159.0,
        "aerialDuels": 901.0,
        "cleanSheets": 6.0,
        "shootingAccuracy": 45.42,
        "successfulCrossesAndCorners": 139.0,
        "unsuccessfulLayoffs": 20.0,
        "duelsWon": 1449.0,
        "penaltiesConceded": 5.0,
        "putthroughBlockedDistribution": 469.0,
        "successfulShortPasses": 9332.0,
        "throwInsToOppositionPlayer": 119.0,
        "successfulOpenPlayPasses": 9466.0,
        "totalClearances": 723.0,
        "goalsConceded": 43.0,
        "groundDuelsLost": 984.0,
        "duels": 2907.0,
        "putthroughBlockedDistributionWon": 222.0,
        "homeGoals": 13.0,
        "possessionPercentage": 47.7,
        "oboxTarget": 32.0,
        "drops": 1.0,
        "tacklesLost": 193.0,
        "lastPlayerTackle": 5.0,
        "successfulPassesOppositionHalf": 5333.0,
        "goalsConcededInsideBox": 34.0,
        "headedGoals": 6.0,
        "iboxBlocked": 66.0,
        "groundDuels": 2006.0,
        "aerialDuelsWon": 427.0,
        "straightRedCards": 1.0,
        "cornersWon": 159.0,
        "successfulDribbles": 218.0,
        "blocks": 121.0,
        "gkUnsuccessfulDistribution": 78.0,
        "interceptions": 228.0,
        "penaltyGoals": 2.0,
        "unsuccessfulLaunches": 434.0,
        "foulAttemptedTackle": 149.0,
        "shotsOnConcededOutsideBox": 31.0,
        "goalConversion": 11.16,
        "expectedGoals": 33.5056,
        "yellowCards": 44.0
      }
    },
    {
      "teamMetadata": {
        "name": "Leeds United",
        "season": "2025",
        "id": "2",
        "shortName": "Leeds",
        "abbr": "LEE"
      },
      "stats": {
        "duelsLost": 1553.0,
        "blockedShots": 103.0,
        "shotsOnTargetIncGoals": 113.0,
        "expectedGoalsOnTarget": 39.5383,
        "gamesPlayed": 29.0,
        "setPiecesGoals": 3.0,
        "crossingAccuracy": 26.64,
        "totalPasses": 11596.0,
        "goals": 37.0,
        "offsides": 49.0,
        "awayGoals": 15.0,
        "tackleSuccess": 59.19,
        "oboxBlocked": 43.0,
        "passingAccuracy": 79.94,
        "iboxTarget": 58.0,
        "aerialDuelsLost": 567.0,
        "goalsConcededOutsideBox": 5.0,
        "groundDuelsWon": 990.0,
        "successfulCornersIntoBox": 47.0,
        "penaltyGoalsConceded": 6.0,
        "expectedGoalsOnTargetConceded": 42.7778,
        "keyPassesAttemptAssists": 222.0,
        "successfulLaunches": 166.0,
        "totalFoulsWon": 325.0,
        "recoveries": 1312.0,
        "pointsGainedFromLosingPositions": 8.0,
        "passingPercentOppHalf": 69.05,
        "shotsOnConcededInsideBox": 96.0,
        "rightFootGoals": 22.0,
        "leftFootGoals": 8.0,
        "unsuccessfulDribbles": 238.0,
        "unsuccessfulCrossesAndCorners": 380.0,
        "otherGoals": 1.0,
        "timesTackled": 485.0,
        "freekickTotal": 8.0,
        "openPlayPasses": 10912.0,
        "gkSuccessfulDistribution": 241.0,
        "shotsOffTargetIncWoodwork": 147.0,
        "totalLossesOfPossession": 3915.0,
        "tacklesWon": 306.0,
        "attemptsFromSetPieces": 8.0,
        "totalShotsConceded": 355.0,
        "totalFoulsConceded": 305.0,
        "unsuccessfulCornersIntoBox": 78.0,
        "successfulLongPasses": 575.0,
        "clearancesOffTheLine": 2.0,
        "throwInsToOwnPlayer": 337.0,
        "touchesInOppBox": 675.0,
        "hitWoodwork": 9.0,
        "successfulPassesOwnHalf": 5337.0,
        "pointsDroppedFromWinningPositions": 17.0,
        "ownGoalsConceded": 1.0,
        "handballsConceded": 12.0,
        "unsuccessfulLongPasses": 942.0,
        "unsuccessfulPassesOwnHalf": 563.0,
        "successfulCrossesOpenPlay": 79.0,
        "expectedAssists": 21.877,
        "totalRedCards": 0.0,
        "expectedGoalsFreekick": 0.496,
        "catches": 18.0,
        "overruns": 32.0,
        "unsuccessfulPassesOppositionHalf": 2143.0,
        "totalShots": 260.0,
        "unsuccessfulShortPasses": 1384.0,
        "goalAssists": 19.0,
        "successfulLayoffs": 248.0,
        "foulWonPenalty": 5.0,
        "unsuccessfulCrossesOpenPlay": 269.0,
        "goalKicks": 222.0,
        "cornersTakenInclShortCorners": 131.0,
        "aerialDuels": 1086.0,
        "cleanSheets": 4.0,
        "shootingAccuracy": 43.46,
        "successfulCrossesAndCorners": 138.0,
        "unsuccessfulLayoffs": 28.0,
        "duelsWon": 1509.0,
        "penaltiesConceded": 6.0,
        "putthroughBlockedDistribution": 477.0,
        "successfulShortPasses": 8695.0,
        "throwInsToOppositionPlayer": 183.0,
        "successfulOpenPlayPasses": 8803.0,
        "totalClearances": 821.0,
        "goalsConceded": 48.0,
        "groundDuelsLost": 986.0,
        "duels": 3062.0,
        "putthroughBlockedDistributionWon": 210.0,
        "homeGoals": 22.0,
        "possessionPercentage": 45.5,
        "oboxTarget": 18.0,
        "drops": 2.0,
        "tacklesLost": 211.0,
        "lastPlayerTackle": 4.0,
        "successfulPassesOppositionHalf": 4071.0,
        "goalsConcededInsideBox": 43.0,
        "headedGoals": 6.0,
        "iboxBlocked": 60.0,
        "groundDuels": 1976.0,
        "aerialDuelsWon": 519.0,
        "straightRedCards": 0.0,
        "cornersWon": 131.0,
        "successfulDribbles": 160.0,
        "blocks": 99.0,
        "gkUnsuccessfulDistribution": 114.0,
        "interceptions": 267.0,
        "penaltyGoals": 4.0,
        "unsuccessfulLaunches": 525.0,
        "foulAttemptedTackle": 138.0,
        "shotsOnConcededOutsideBox": 25.0,
        "goalConversion": 14.23,
        "expectedGoals": 41.4291,
        "yellowCards": 46.0
      }
    },
    {
      "teamMetadata": {
        "name": "West Ham United",
        "season": "2025",
        "id": "21",
        "shortName": "West Ham",
        "abbr": "WHU"
      },
      "stats": {
        "duelsLost": 1418.0,
        "blockedShots": 91.0,
        "shotsOnTargetIncGoals": 102.0,
        "expectedGoalsOnTarget": 32.6804,
        "gamesPlayed": 29.0,
        "crossingAccuracy": 21.38,
        "totalPasses": 10880.0,
        "goals": 35.0,
        "offsides": 53.0,
        "awayGoals": 18.0,
        "tackleSuccess": 60.0,
        "redCard2ndYellow": 1.0,
        "oboxBlocked": 33.0,
        "passingAccuracy": 79.17,
        "iboxTarget": 50.0,
        "aerialDuelsLost": 470.0,
        "goalsConcededOutsideBox": 3.0,
        "ownGoalsAccrued": 2.0,
        "groundDuelsWon": 999.0,
        "successfulCornersIntoBox": 33.0,
        "penaltyGoalsConceded": 5.0,
        "expectedGoalsOnTargetConceded": 49.2954,
        "keyPassesAttemptAssists": 199.0,
        "successfulLaunches": 158.0,
        "totalFoulsWon": 310.0,
        "recoveries": 1330.0,
        "pointsGainedFromLosingPositions": 8.0,
        "passingPercentOppHalf": 70.83,
        "shotsOnConcededInsideBox": 123.0,
        "rightFootGoals": 11.0,
        "leftFootGoals": 14.0,
        "unsuccessfulDribbles": 216.0,
        "unsuccessfulCrossesAndCorners": 375.0,
        "otherGoals": 1.0,
        "timesTackled": 470.0,
        "freekickTotal": 4.0,
        "openPlayPasses": 10214.0,
        "gkSuccessfulDistribution": 269.0,
        "shotsOffTargetIncWoodwork": 111.0,
        "totalLossesOfPossession": 3735.0,
        "tacklesWon": 300.0,
        "attemptsFromSetPieces": 4.0,
        "totalShotsConceded": 428.0,
        "totalFoulsConceded": 320.0,
        "unsuccessfulCornersIntoBox": 106.0,
        "successfulLongPasses": 588.0,
        "clearancesOffTheLine": 4.0,
        "throwInsToOwnPlayer": 424.0,
        "touchesInOppBox": 572.0,
        "hitWoodwork": 3.0,
        "successfulPassesOwnHalf": 4363.0,
        "pointsDroppedFromWinningPositions": 20.0,
        "ownGoalsConceded": 2.0,
        "handballsConceded": 14.0,
        "unsuccessfulLongPasses": 935.0,
        "unsuccessfulPassesOwnHalf": 515.0,
        "successfulCrossesOpenPlay": 61.0,
        "expectedAssists": 18.6648,
        "totalRedCards": 3.0,
        "expectedGoalsFreekick": 0.2818,
        "catches": 26.0,
        "overruns": 30.0,
        "unsuccessfulPassesOppositionHalf": 2126.0,
        "totalShots": 213.0,
        "unsuccessfulShortPasses": 1331.0,
        "goalAssists": 21.0,
        "successfulLayoffs": 239.0,
        "foulWonPenalty": 3.0,
        "unsuccessfulCrossesOpenPlay": 243.0,
        "goalKicks": 242.0,
        "cornersTakenInclShortCorners": 149.0,
        "aerialDuels": 912.0,
        "cleanSheets": 4.0,
        "shootingAccuracy": 47.89,
        "successfulCrossesAndCorners": 102.0,
        "unsuccessfulLayoffs": 24.0,
        "duelsWon": 1441.0,
        "penaltiesConceded": 6.0,
        "putthroughBlockedDistribution": 451.0,
        "successfulShortPasses": 8026.0,
        "throwInsToOppositionPlayer": 95.0,
        "successfulOpenPlayPasses": 8176.0,
        "totalClearances": 885.0,
        "goalsConceded": 54.0,
        "groundDuelsLost": 948.0,
        "duels": 2859.0,
        "putthroughBlockedDistributionWon": 209.0,
        "homeGoals": 17.0,
        "possessionPercentage": 42.7,
        "oboxTarget": 19.0,
        "tacklesLost": 200.0,
        "lastPlayerTackle": 4.0,
        "successfulPassesOppositionHalf": 4353.0,
        "goalsConcededInsideBox": 51.0,
        "headedGoals": 7.0,
        "iboxBlocked": 58.0,
        "groundDuels": 1947.0,
        "aerialDuelsWon": 442.0,
        "straightRedCards": 2.0,
        "cornersWon": 149.0,
        "successfulDribbles": 194.0,
        "blocks": 124.0,
        "gkUnsuccessfulDistribution": 118.0,
        "interceptions": 275.0,
        "penaltyGoals": 3.0,
        "unsuccessfulLaunches": 515.0,
        "foulAttemptedTackle": 157.0,
        "shotsOnConcededOutsideBox": 34.0,
        "goalConversion": 16.43,
        "expectedGoals": 34.9794,
        "yellowCards": 50.0
      }
    },
    {
      "teamMetadata": {
        "name": "Arsenal",
        "season": "2025",
        "id": "3",
        "shortName": "Arsenal",
        "abbr": "ARS"
      },
      "stats": {
        "duelsLost": 1380.0,
        "blockedShots": 125.0,
        "shotsOnTargetIncGoals": 147.0,
        "expectedGoalsOnTarget": 48.215,
        "gamesPlayed": 30.0,
        "crossingAccuracy": 24.42,
        "totalPasses": 14137.0,
        "goals": 59.0,
        "offsides": 43.0,
        "awayGoals": 26.0,
        "tackleSuccess": 55.06,
        "oboxBlocked": 34.0,
        "passingAccuracy": 84.18,
        "iboxTarget": 67.0,
        "aerialDuelsLost": 451.0,
        "goalsConcededOutsideBox": 6.0,
        "ownGoalsAccrued": 4.0,
        "groundDuelsWon": 1021.0,
        "successfulCornersIntoBox": 44.0,
        "expectedGoalsOnTargetConceded": 20.6877,
        "keyPassesAttemptAssists": 274.0,
        "successfulLaunches": 165.0,
        "totalFoulsWon": 316.0,
        "recoveries": 1370.0,
        "pointsGainedFromLosingPositions": 9.0,
        "passingPercentOppHalf": 78.25,
        "shotsOnConcededInsideBox": 52.0,
        "rightFootGoals": 30.0,
        "leftFootGoals": 11.0,
        "unsuccessfulDribbles": 237.0,
        "unsuccessfulCrossesAndCorners": 421.0,
        "timesTackled": 484.0,
        "freekickTotal": 6.0,
        "openPlayPasses": 13592.0,
        "gkSuccessfulDistribution": 257.0,
        "shotsOffTargetIncWoodwork": 158.0,
        "totalLossesOfPossession": 3761.0,
        "tacklesWon": 272.0,
        "attemptsFromSetPieces": 6.0,
        "totalShotsConceded": 233.0,
        "totalFoulsConceded": 305.0,
        "unsuccessfulCornersIntoBox": 111.0,
        "successfulLongPasses": 559.0,
        "clearancesOffTheLine": 2.0,
        "throwInsToOwnPlayer": 410.0,
        "touchesInOppBox": 999.0,
        "hitWoodwork": 8.0,
        "successfulPassesOwnHalf": 5570.0,
        "pointsDroppedFromWinningPositions": 9.0,
        "ownGoalsConceded": 1.0,
        "handballsConceded": 7.0,
        "unsuccessfulLongPasses": 778.0,
        "unsuccessfulPassesOwnHalf": 476.0,
        "successfulCrossesOpenPlay": 81.0,
        "expectedAssists": 34.7758,
        "totalRedCards": 0.0,
        "expectedGoalsFreekick": 0.2068,
        "catches": 29.0,
        "overruns": 32.0,
        "unsuccessfulPassesOppositionHalf": 2181.0,
        "totalShots": 305.0,
        "unsuccessfulShortPasses": 1458.0,
        "goalAssists": 41.0,
        "successfulLayoffs": 178.0,
        "foulWonPenalty": 3.0,
        "unsuccessfulCrossesOpenPlay": 281.0,
        "goalKicks": 158.0,
        "cornersTakenInclShortCorners": 173.0,
        "aerialDuels": 945.0,
        "cleanSheets": 14.0,
        "shootingAccuracy": 48.2,
        "successfulCrossesAndCorners": 136.0,
        "unsuccessfulLayoffs": 32.0,
        "duelsWon": 1515.0,
        "putthroughBlockedDistribution": 432.0,
        "successfulShortPasses": 11342.0,
        "throwInsToOppositionPlayer": 96.0,
        "successfulOpenPlayPasses": 11487.0,
        "totalClearances": 717.0,
        "goalsConceded": 22.0,
        "groundDuelsLost": 929.0,
        "duels": 2895.0,
        "putthroughBlockedDistributionWon": 185.0,
        "homeGoals": 33.0,
        "possessionPercentage": 56.3,
        "oboxTarget": 25.0,
        "drops": 6.0,
        "tacklesLost": 222.0,
        "lastPlayerTackle": 10.0,
        "successfulPassesOppositionHalf": 6467.0,
        "goalsConcededInsideBox": 16.0,
        "headedGoals": 14.0,
        "iboxBlocked": 91.0,
        "groundDuels": 1950.0,
        "aerialDuelsWon": 494.0,
        "straightRedCards": 0.0,
        "cornersWon": 173.0,
        "successfulDribbles": 219.0,
        "blocks": 76.0,
        "gkUnsuccessfulDistribution": 52.0,
        "interceptions": 218.0,
        "penaltyGoals": 3.0,
        "unsuccessfulLaunches": 481.0,
        "foulAttemptedTackle": 148.0,
        "shotsOnConcededOutsideBox": 18.0,
        "goalConversion": 19.34,
        "expectedGoals": 49.9767,
        "yellowCards": 40.0
      }
    },
    {
      "teamMetadata": {
        "name": "Crystal Palace",
        "season": "2025",
        "id": "31",
        "shortName": "Crystal Palace",
        "abbr": "CRY"
      },
      "stats": {
        "duelsLost": 1528.0,
        "penaltiesSaved": 1.0,
        "blockedShots": 103.0,
        "shotsOnTargetIncGoals": 110.0,
        "expectedGoalsOnTarget": 36.7492,
        "gamesPlayed": 29.0,
        "crossingAccuracy": 22.08,
        "totalPasses": 11398.0,
        "goals": 33.0,
        "offsides": 54.0,
        "awayGoals": 19.0,
        "tackleSuccess": 59.49,
        "redCard2ndYellow": 1.0,
        "oboxBlocked": 42.0,
        "passingAccuracy": 78.02,
        "iboxTarget": 61.0,
        "aerialDuelsLost": 591.0,
        "goalsConcededOutsideBox": 4.0,
        "ownGoalsAccrued": 1.0,
        "groundDuelsWon": 928.0,
        "successfulCornersIntoBox": 35.0,
        "penaltyGoalsConceded": 4.0,
        "expectedGoalsOnTargetConceded": 39.3971,
        "keyPassesAttemptAssists": 205.0,
        "successfulLaunches": 146.0,
        "totalFoulsWon": 265.0,
        "recoveries": 1348.0,
        "pointsGainedFromLosingPositions": 5.0,
        "passingPercentOppHalf": 68.27,
        "shotsOnConcededInsideBox": 98.0,
        "rightFootGoals": 18.0,
        "leftFootGoals": 5.0,
        "unsuccessfulDribbles": 171.0,
        "unsuccessfulCrossesAndCorners": 360.0,
        "timesTackled": 430.0,
        "freekickTotal": 5.0,
        "openPlayPasses": 10800.0,
        "gkSuccessfulDistribution": 241.0,
        "shotsOffTargetIncWoodwork": 125.0,
        "totalLossesOfPossession": 3899.0,
        "tacklesWon": 326.0,
        "attemptsFromSetPieces": 5.0,
        "totalShotsConceded": 335.0,
        "totalFoulsConceded": 309.0,
        "unsuccessfulCornersIntoBox": 77.0,
        "successfulLongPasses": 571.0,
        "clearancesOffTheLine": 4.0,
        "throwInsToOwnPlayer": 367.0,
        "touchesInOppBox": 709.0,
        "hitWoodwork": 11.0,
        "successfulPassesOwnHalf": 4833.0,
        "pointsDroppedFromWinningPositions": 19.0,
        "ownGoalsConceded": 1.0,
        "handballsConceded": 17.0,
        "unsuccessfulLongPasses": 994.0,
        "unsuccessfulPassesOwnHalf": 618.0,
        "successfulCrossesOpenPlay": 65.0,
        "expectedAssists": 28.4944,
        "totalRedCards": 2.0,
        "expectedGoalsFreekick": 0.3189,
        "catches": 19.0,
        "overruns": 18.0,
        "unsuccessfulPassesOppositionHalf": 2247.0,
        "totalShots": 235.0,
        "unsuccessfulShortPasses": 1511.0,
        "goalAssists": 20.0,
        "successfulLayoffs": 175.0,
        "foulWonPenalty": 6.0,
        "unsuccessfulCrossesOpenPlay": 255.0,
        "goalKicks": 223.0,
        "cornersTakenInclShortCorners": 121.0,
        "aerialDuels": 1145.0,
        "cleanSheets": 10.0,
        "shootingAccuracy": 46.81,
        "successfulCrossesAndCorners": 102.0,
        "unsuccessfulLayoffs": 18.0,
        "duelsWon": 1482.0,
        "penaltiesConceded": 5.0,
        "putthroughBlockedDistribution": 499.0,
        "successfulShortPasses": 8322.0,
        "throwInsToOppositionPlayer": 124.0,
        "successfulOpenPlayPasses": 8495.0,
        "totalClearances": 949.0,
        "goalsConceded": 35.0,
        "groundDuelsLost": 937.0,
        "duels": 3010.0,
        "putthroughBlockedDistributionWon": 253.0,
        "homeGoals": 14.0,
        "possessionPercentage": 45.2,
        "oboxTarget": 17.0,
        "tacklesLost": 222.0,
        "lastPlayerTackle": 7.0,
        "successfulPassesOppositionHalf": 4162.0,
        "goalsConcededInsideBox": 31.0,
        "headedGoals": 9.0,
        "iboxBlocked": 61.0,
        "groundDuels": 1865.0,
        "aerialDuelsWon": 554.0,
        "straightRedCards": 1.0,
        "cornersWon": 121.0,
        "successfulDribbles": 121.0,
        "blocks": 78.0,
        "gkUnsuccessfulDistribution": 98.0,
        "interceptions": 249.0,
        "penaltyGoals": 6.0,
        "unsuccessfulLaunches": 551.0,
        "foulAttemptedTackle": 169.0,
        "shotsOnConcededOutsideBox": 27.0,
        "goalConversion": 14.04,
        "expectedGoals": 45.077,
        "yellowCards": 60.0
      }
    },
    {
      "teamMetadata": {
        "name": "Brighton and Hove Albion",
        "season": "2025",
        "id": "36",
        "shortName": "Brighton",
        "abbr": "BHA"
      },
      "stats": {
        "duelsLost": 1551.0,
        "penaltiesSaved": 1.0,
        "blockedShots": 100.0,
        "shotsOnTargetIncGoals": 127.0,
        "expectedGoalsOnTarget": 39.4803,
        "gamesPlayed": 29.0,
        "setPiecesGoals": 1.0,
        "crossingAccuracy": 26.15,
        "totalPasses": 13709.0,
        "goals": 38.0,
        "offsides": 55.0,
        "awayGoals": 16.0,
        "tackleSuccess": 60.04,
        "oboxBlocked": 43.0,
        "passingAccuracy": 84.02,
        "iboxTarget": 55.0,
        "aerialDuelsLost": 434.0,
        "goalsConcededOutsideBox": 7.0,
        "ownGoalsAccrued": 1.0,
        "groundDuelsWon": 1032.0,
        "successfulCornersIntoBox": 36.0,
        "penaltyGoalsConceded": 5.0,
        "expectedGoalsOnTargetConceded": 36.3619,
        "keyPassesAttemptAssists": 246.0,
        "successfulLaunches": 101.0,
        "totalFoulsWon": 290.0,
        "recoveries": 1426.0,
        "pointsGainedFromLosingPositions": 14.0,
        "passingPercentOppHalf": 75.36,
        "shotsOnConcededInsideBox": 88.0,
        "rightFootGoals": 25.0,
        "leftFootGoals": 7.0,
        "unsuccessfulDribbles": 261.0,
        "unsuccessfulCrossesAndCorners": 370.0,
        "timesTackled": 530.0,
        "freekickTotal": 11.0,
        "openPlayPasses": 13089.0,
        "gkSuccessfulDistribution": 301.0,
        "shotsOffTargetIncWoodwork": 143.0,
        "totalLossesOfPossession": 3775.0,
        "tacklesWon": 320.0,
        "attemptsFromSetPieces": 11.0,
        "totalShotsConceded": 351.0,
        "totalFoulsConceded": 351.0,
        "unsuccessfulCornersIntoBox": 84.0,
        "successfulLongPasses": 600.0,
        "clearancesOffTheLine": 3.0,
        "throwInsToOwnPlayer": 390.0,
        "touchesInOppBox": 776.0,
        "hitWoodwork": 10.0,
        "successfulPassesOwnHalf": 6531.0,
        "pointsDroppedFromWinningPositions": 12.0,
        "ownGoalsConceded": 4.0,
        "handballsConceded": 12.0,
        "unsuccessfulLongPasses": 742.0,
        "unsuccessfulPassesOwnHalf": 560.0,
        "successfulCrossesOpenPlay": 88.0,
        "expectedAssists": 23.916,
        "totalRedCards": 0.0,
        "expectedGoalsFreekick": 0.671,
        "catches": 15.0,
        "overruns": 39.0,
        "unsuccessfulPassesOppositionHalf": 2001.0,
        "totalShots": 270.0,
        "unsuccessfulShortPasses": 1449.0,
        "goalAssists": 22.0,
        "successfulLayoffs": 248.0,
        "foulWonPenalty": 5.0,
        "unsuccessfulCrossesOpenPlay": 271.0,
        "goalKicks": 229.0,
        "cornersTakenInclShortCorners": 140.0,
        "aerialDuels": 867.0,
        "cleanSheets": 6.0,
        "shootingAccuracy": 47.04,
        "successfulCrossesAndCorners": 131.0,
        "unsuccessfulLayoffs": 33.0,
        "duelsWon": 1465.0,
        "penaltiesConceded": 6.0,
        "putthroughBlockedDistribution": 469.0,
        "successfulShortPasses": 10918.0,
        "throwInsToOppositionPlayer": 84.0,
        "successfulOpenPlayPasses": 10992.0,
        "totalClearances": 682.0,
        "goalsConceded": 36.0,
        "groundDuelsLost": 1117.0,
        "duels": 3016.0,
        "putthroughBlockedDistributionWon": 236.0,
        "homeGoals": 22.0,
        "possessionPercentage": 52.9,
        "oboxTarget": 35.0,
        "tacklesLost": 213.0,
        "lastPlayerTackle": 5.0,
        "successfulPassesOppositionHalf": 5118.0,
        "goalsConcededInsideBox": 29.0,
        "headedGoals": 5.0,
        "iboxBlocked": 57.0,
        "groundDuels": 2149.0,
        "aerialDuelsWon": 433.0,
        "straightRedCards": 0.0,
        "cornersWon": 140.0,
        "successfulDribbles": 215.0,
        "blocks": 85.0,
        "gkUnsuccessfulDistribution": 34.0,
        "interceptions": 242.0,
        "penaltyGoals": 3.0,
        "unsuccessfulLaunches": 383.0,
        "foulAttemptedTackle": 197.0,
        "shotsOnConcededOutsideBox": 29.0,
        "goalConversion": 14.07,
        "expectedGoals": 42.0955,
        "yellowCards": 72.0
      }
    },
    {
      "teamMetadata": {
        "name": "Wolverhampton Wanderers",
        "season": "2025",
        "id": "39",
        "shortName": "Wolves",
        "abbr": "WOL"
      },
      "stats": {
        "duelsLost": 1598.0,
        "blockedShots": 68.0,
        "shotsOnTargetIncGoals": 97.0,
        "expectedGoalsOnTarget": 25.9057,
        "gamesPlayed": 30.0,
        "crossingAccuracy": 26.84,
        "totalPasses": 11122.0,
        "goals": 22.0,
        "offsides": 40.0,
        "awayGoals": 5.0,
        "tackleSuccess": 58.42,
        "redCard2ndYellow": 1.0,
        "oboxBlocked": 34.0,
        "passingAccuracy": 79.75,
        "iboxTarget": 55.0,
        "aerialDuelsLost": 516.0,
        "goalsConcededOutsideBox": 9.0,
        "ownGoalsAccrued": 1.0,
        "groundDuelsWon": 1098.0,
        "successfulCornersIntoBox": 24.0,
        "penaltyGoalsConceded": 3.0,
        "expectedGoalsOnTargetConceded": 43.8316,
        "keyPassesAttemptAssists": 182.0,
        "successfulLaunches": 166.0,
        "totalFoulsWon": 321.0,
        "recoveries": 1388.0,
        "pointsGainedFromLosingPositions": 3.0,
        "passingPercentOppHalf": 71.29,
        "shotsOnConcededInsideBox": 108.0,
        "rightFootGoals": 14.0,
        "leftFootGoals": 4.0,
        "unsuccessfulDribbles": 213.0,
        "unsuccessfulCrossesAndCorners": 398.0,
        "timesTackled": 476.0,
        "freekickTotal": 13.0,
        "openPlayPasses": 10407.0,
        "gkSuccessfulDistribution": 262.0,
        "shotsOffTargetIncWoodwork": 108.0,
        "totalLossesOfPossession": 3822.0,
        "tacklesWon": 340.0,
        "attemptsFromSetPieces": 13.0,
        "totalShotsConceded": 420.0,
        "totalFoulsConceded": 399.0,
        "unsuccessfulCornersIntoBox": 65.0,
        "successfulLongPasses": 647.0,
        "clearancesOffTheLine": 4.0,
        "throwInsToOwnPlayer": 415.0,
        "touchesInOppBox": 570.0,
        "hitWoodwork": 8.0,
        "successfulPassesOwnHalf": 4801.0,
        "pointsDroppedFromWinningPositions": 7.0,
        "ownGoalsConceded": 4.0,
        "handballsConceded": 9.0,
        "unsuccessfulLongPasses": 919.0,
        "unsuccessfulPassesOwnHalf": 613.0,
        "successfulCrossesOpenPlay": 109.0,
        "expectedAssists": 17.7746,
        "totalRedCards": 3.0,
        "expectedGoalsFreekick": 0.8002,
        "catches": 29.0,
        "overruns": 25.0,
        "unsuccessfulPassesOppositionHalf": 2037.0,
        "totalShots": 205.0,
        "unsuccessfulShortPasses": 1333.0,
        "goalAssists": 14.0,
        "successfulLayoffs": 191.0,
        "foulWonPenalty": 4.0,
        "unsuccessfulCrossesOpenPlay": 310.0,
        "goalKicks": 246.0,
        "cornersTakenInclShortCorners": 95.0,
        "aerialDuels": 984.0,
        "cleanSheets": 4.0,
        "shootingAccuracy": 47.32,
        "successfulCrossesAndCorners": 146.0,
        "unsuccessfulLayoffs": 34.0,
        "duelsWon": 1566.0,
        "penaltiesConceded": 3.0,
        "putthroughBlockedDistribution": 475.0,
        "successfulShortPasses": 8223.0,
        "throwInsToOppositionPlayer": 136.0,
        "successfulOpenPlayPasses": 8408.0,
        "totalClearances": 887.0,
        "goalsConceded": 52.0,
        "groundDuelsLost": 1082.0,
        "duels": 3164.0,
        "putthroughBlockedDistributionWon": 228.0,
        "homeGoals": 17.0,
        "possessionPercentage": 42.9,
        "oboxTarget": 21.0,
        "drops": 6.0,
        "tacklesLost": 242.0,
        "lastPlayerTackle": 10.0,
        "successfulPassesOppositionHalf": 4215.0,
        "goalsConcededInsideBox": 43.0,
        "headedGoals": 3.0,
        "iboxBlocked": 34.0,
        "groundDuels": 2180.0,
        "aerialDuelsWon": 468.0,
        "straightRedCards": 2.0,
        "cornersWon": 95.0,
        "successfulDribbles": 201.0,
        "blocks": 115.0,
        "gkUnsuccessfulDistribution": 118.0,
        "interceptions": 258.0,
        "penaltyGoals": 2.0,
        "unsuccessfulLaunches": 426.0,
        "foulAttemptedTackle": 218.0,
        "shotsOnConcededOutsideBox": 36.0,
        "goalConversion": 10.73,
        "expectedGoals": 26.6933,
        "yellowCards": 62.0
      }
    },
    {
      "teamMetadata": {
        "name": "Newcastle United",
        "season": "2025",
        "id": "4",
        "shortName": "Newcastle",
        "abbr": "NEW"
      },
      "stats": {
        "duelsLost": 1435.0,
        "blockedShots": 113.0,
        "shotsOnTargetIncGoals": 137.0,
        "expectedGoalsOnTarget": 45.0417,
        "gamesPlayed": 29.0,
        "crossingAccuracy": 21.46,
        "totalPasses": 13157.0,
        "goals": 42.0,
        "offsides": 42.0,
        "awayGoals": 14.0,
        "tackleSuccess": 64.29,
        "redCard2ndYellow": 2.0,
        "oboxBlocked": 50.0,
        "passingAccuracy": 83.57,
        "iboxTarget": 70.0,
        "aerialDuelsLost": 447.0,
        "goalsConcededOutsideBox": 6.0,
        "groundDuelsWon": 937.0,
        "successfulCornersIntoBox": 42.0,
        "penaltyGoalsConceded": 4.0,
        "expectedGoalsOnTargetConceded": 37.5151,
        "keyPassesAttemptAssists": 250.0,
        "successfulLaunches": 97.0,
        "totalFoulsWon": 321.0,
        "recoveries": 1450.0,
        "pointsGainedFromLosingPositions": 3.0,
        "passingPercentOppHalf": 77.76,
        "shotsOnConcededInsideBox": 92.0,
        "rightFootGoals": 24.0,
        "leftFootGoals": 10.0,
        "unsuccessfulDribbles": 226.0,
        "unsuccessfulCrossesAndCorners": 571.0,
        "timesTackled": 489.0,
        "freekickTotal": 8.0,
        "openPlayPasses": 12529.0,
        "gkSuccessfulDistribution": 303.0,
        "shotsOffTargetIncWoodwork": 136.0,
        "totalLossesOfPossession": 3823.0,
        "tacklesWon": 270.0,
        "attemptsFromSetPieces": 8.0,
        "totalShotsConceded": 331.0,
        "totalFoulsConceded": 300.0,
        "unsuccessfulCornersIntoBox": 132.0,
        "successfulLongPasses": 619.0,
        "clearancesOffTheLine": 1.0,
        "throwInsToOwnPlayer": 452.0,
        "touchesInOppBox": 767.0,
        "hitWoodwork": 16.0,
        "successfulPassesOwnHalf": 5268.0,
        "pointsDroppedFromWinningPositions": 19.0,
        "ownGoalsConceded": 2.0,
        "handballsConceded": 15.0,
        "unsuccessfulLongPasses": 756.0,
        "unsuccessfulPassesOwnHalf": 524.0,
        "successfulCrossesOpenPlay": 106.0,
        "expectedAssists": 27.8733,
        "totalRedCards": 3.0,
        "expectedGoalsFreekick": 0.3725,
        "catches": 28.0,
        "overruns": 37.0,
        "unsuccessfulPassesOppositionHalf": 2209.0,
        "totalShots": 273.0,
        "unsuccessfulShortPasses": 1406.0,
        "goalAssists": 23.0,
        "successfulLayoffs": 212.0,
        "foulWonPenalty": 6.0,
        "unsuccessfulCrossesOpenPlay": 421.0,
        "goalKicks": 206.0,
        "cornersTakenInclShortCorners": 195.0,
        "aerialDuels": 965.0,
        "cleanSheets": 7.0,
        "shootingAccuracy": 50.18,
        "successfulCrossesAndCorners": 156.0,
        "unsuccessfulLayoffs": 22.0,
        "duelsWon": 1455.0,
        "penaltiesConceded": 4.0,
        "putthroughBlockedDistribution": 448.0,
        "successfulShortPasses": 10376.0,
        "throwInsToOppositionPlayer": 75.0,
        "successfulOpenPlayPasses": 10558.0,
        "totalClearances": 768.0,
        "goalsConceded": 43.0,
        "groundDuelsLost": 988.0,
        "duels": 2890.0,
        "putthroughBlockedDistributionWon": 207.0,
        "homeGoals": 28.0,
        "possessionPercentage": 53.3,
        "oboxTarget": 25.0,
        "drops": 7.0,
        "tacklesLost": 150.0,
        "lastPlayerTackle": 6.0,
        "successfulPassesOppositionHalf": 5883.0,
        "goalsConcededInsideBox": 37.0,
        "headedGoals": 8.0,
        "iboxBlocked": 63.0,
        "groundDuels": 1925.0,
        "aerialDuelsWon": 518.0,
        "straightRedCards": 1.0,
        "cornersWon": 195.0,
        "successfulDribbles": 204.0,
        "blocks": 90.0,
        "gkUnsuccessfulDistribution": 98.0,
        "interceptions": 205.0,
        "penaltyGoals": 6.0,
        "unsuccessfulLaunches": 379.0,
        "foulAttemptedTackle": 142.0,
        "shotsOnConcededOutsideBox": 32.0,
        "goalConversion": 15.38,
        "expectedGoals": 44.0308,
        "yellowCards": 47.0
      }
    },
    {
      "teamMetadata": {
        "name": "Manchester City",
        "season": "2025",
        "id": "43",
        "shortName": "Man City",
        "abbr": "MCI"
      },
      "stats": {
        "duelsLost": 1287.0,
        "penaltiesSaved": 1.0,
        "blockedShots": 114.0,
        "shotsOnTargetIncGoals": 151.0,
        "expectedGoalsOnTarget": 46.874,
        "gamesPlayed": 29.0,
        "crossingAccuracy": 28.99,
        "totalPasses": 16852.0,
        "goals": 59.0,
        "offsides": 38.0,
        "awayGoals": 23.0,
        "tackleSuccess": 60.27,
        "oboxBlocked": 41.0,
        "passingAccuracy": 88.37,
        "iboxTarget": 82.0,
        "aerialDuelsLost": 277.0,
        "goalsConcededOutsideBox": 7.0,
        "ownGoalsAccrued": 3.0,
        "groundDuelsWon": 1047.0,
        "successfulCornersIntoBox": 54.0,
        "penaltyGoalsConceded": 1.0,
        "expectedGoalsOnTargetConceded": 31.1859,
        "keyPassesAttemptAssists": 283.0,
        "successfulLaunches": 83.0,
        "totalFoulsWon": 316.0,
        "recoveries": 1335.0,
        "pointsGainedFromLosingPositions": 3.0,
        "passingPercentOppHalf": 85.72,
        "shotsOnConcededInsideBox": 76.0,
        "rightFootGoals": 17.0,
        "leftFootGoals": 31.0,
        "unsuccessfulDribbles": 299.0,
        "unsuccessfulCrossesAndCorners": 316.0,
        "timesTackled": 574.0,
        "freekickTotal": 7.0,
        "openPlayPasses": 16216.0,
        "gkSuccessfulDistribution": 236.0,
        "shotsOffTargetIncWoodwork": 153.0,
        "totalLossesOfPossession": 3436.0,
        "tacklesWon": 264.0,
        "attemptsFromSetPieces": 7.0,
        "totalShotsConceded": 292.0,
        "totalFoulsConceded": 293.0,
        "unsuccessfulCornersIntoBox": 85.0,
        "successfulLongPasses": 566.0,
        "clearancesOffTheLine": 2.0,
        "throwInsToOwnPlayer": 436.0,
        "touchesInOppBox": 969.0,
        "hitWoodwork": 12.0,
        "successfulPassesOwnHalf": 6497.0,
        "pointsDroppedFromWinningPositions": 13.0,
        "handballsConceded": 8.0,
        "unsuccessfulLongPasses": 566.0,
        "unsuccessfulPassesOwnHalf": 561.0,
        "successfulCrossesOpenPlay": 72.0,
        "expectedAssists": 37.3638,
        "totalRedCards": 0.0,
        "expectedGoalsFreekick": 0.3978,
        "catches": 12.0,
        "overruns": 44.0,
        "unsuccessfulPassesOppositionHalf": 1715.0,
        "totalShots": 304.0,
        "unsuccessfulShortPasses": 1394.0,
        "goalAssists": 45.0,
        "successfulLayoffs": 332.0,
        "foulWonPenalty": 4.0,
        "unsuccessfulCrossesOpenPlay": 215.0,
        "goalKicks": 172.0,
        "cornersTakenInclShortCorners": 158.0,
        "aerialDuels": 655.0,
        "cleanSheets": 12.0,
        "shootingAccuracy": 49.67,
        "successfulCrossesAndCorners": 129.0,
        "unsuccessfulLayoffs": 23.0,
        "duelsWon": 1425.0,
        "penaltiesConceded": 2.0,
        "putthroughBlockedDistribution": 455.0,
        "successfulShortPasses": 14326.0,
        "throwInsToOppositionPlayer": 66.0,
        "successfulOpenPlayPasses": 14341.0,
        "totalClearances": 661.0,
        "goalsConceded": 27.0,
        "groundDuelsLost": 1010.0,
        "duels": 2712.0,
        "putthroughBlockedDistributionWon": 198.0,
        "homeGoals": 36.0,
        "possessionPercentage": 59.5,
        "oboxTarget": 13.0,
        "drops": 3.0,
        "tacklesLost": 174.0,
        "lastPlayerTackle": 8.0,
        "successfulPassesOppositionHalf": 8524.0,
        "goalsConcededInsideBox": 20.0,
        "headedGoals": 8.0,
        "iboxBlocked": 73.0,
        "groundDuels": 2057.0,
        "aerialDuelsWon": 378.0,
        "straightRedCards": 0.0,
        "cornersWon": 158.0,
        "successfulDribbles": 296.0,
        "blocks": 79.0,
        "gkUnsuccessfulDistribution": 34.0,
        "interceptions": 232.0,
        "penaltyGoals": 3.0,
        "unsuccessfulLaunches": 287.0,
        "foulAttemptedTackle": 135.0,
        "shotsOnConcededOutsideBox": 26.0,
        "goalConversion": 19.41,
        "expectedGoals": 53.2265,
        "yellowCards": 54.0
      }
    },
    {
      "teamMetadata": {
        "name": "Fulham",
        "season": "2025",
        "id": "54",
        "shortName": "Fulham",
        "abbr": "FUL"
      },
      "stats": {
        "duelsLost": 1329.0,
        "blockedShots": 109.0,
        "shotsOnTargetIncGoals": 109.0,
        "expectedGoalsOnTarget": 37.2732,
        "gamesPlayed": 29.0,
        "setPiecesGoals": 1.0,
        "crossingAccuracy": 26.87,
        "totalPasses": 13855.0,
        "goals": 40.0,
        "offsides": 50.0,
        "awayGoals": 16.0,
        "tackleSuccess": 57.11,
        "oboxBlocked": 39.0,
        "passingAccuracy": 83.88,
        "iboxTarget": 49.0,
        "aerialDuelsLost": 434.0,
        "goalsConcededOutsideBox": 4.0,
        "ownGoalsAccrued": 4.0,
        "groundDuelsWon": 920.0,
        "successfulCornersIntoBox": 38.0,
        "penaltyGoalsConceded": 3.0,
        "expectedGoalsOnTargetConceded": 36.6218,
        "keyPassesAttemptAssists": 234.0,
        "successfulLaunches": 107.0,
        "totalFoulsWon": 262.0,
        "recoveries": 1316.0,
        "pointsGainedFromLosingPositions": 10.0,
        "passingPercentOppHalf": 76.47,
        "shotsOnConcededInsideBox": 89.0,
        "rightFootGoals": 13.0,
        "leftFootGoals": 16.0,
        "unsuccessfulDribbles": 213.0,
        "unsuccessfulCrossesAndCorners": 381.0,
        "timesTackled": 438.0,
        "freekickTotal": 8.0,
        "openPlayPasses": 13209.0,
        "gkSuccessfulDistribution": 298.0,
        "shotsOffTargetIncWoodwork": 137.0,
        "totalLossesOfPossession": 3659.0,
        "tacklesWon": 281.0,
        "attemptsFromSetPieces": 8.0,
        "totalShotsConceded": 341.0,
        "totalFoulsConceded": 322.0,
        "unsuccessfulCornersIntoBox": 81.0,
        "successfulLongPasses": 639.0,
        "clearancesOffTheLine": 3.0,
        "throwInsToOwnPlayer": 477.0,
        "touchesInOppBox": 700.0,
        "hitWoodwork": 7.0,
        "successfulPassesOwnHalf": 6566.0,
        "pointsDroppedFromWinningPositions": 11.0,
        "ownGoalsConceded": 3.0,
        "handballsConceded": 10.0,
        "unsuccessfulLongPasses": 791.0,
        "unsuccessfulPassesOwnHalf": 677.0,
        "successfulCrossesOpenPlay": 96.0,
        "expectedAssists": 25.2411,
        "totalRedCards": 0.0,
        "expectedGoalsFreekick": 0.7735,
        "catches": 21.0,
        "overruns": 23.0,
        "unsuccessfulPassesOppositionHalf": 1937.0,
        "totalShots": 246.0,
        "unsuccessfulShortPasses": 1442.0,
        "goalAssists": 24.0,
        "successfulLayoffs": 231.0,
        "foulWonPenalty": 3.0,
        "unsuccessfulCrossesOpenPlay": 282.0,
        "goalKicks": 236.0,
        "cornersTakenInclShortCorners": 137.0,
        "aerialDuels": 849.0,
        "cleanSheets": 5.0,
        "shootingAccuracy": 44.31,
        "successfulCrossesAndCorners": 140.0,
        "unsuccessfulLayoffs": 21.0,
        "duelsWon": 1335.0,
        "penaltiesConceded": 4.0,
        "putthroughBlockedDistribution": 469.0,
        "successfulShortPasses": 10983.0,
        "throwInsToOppositionPlayer": 101.0,
        "successfulOpenPlayPasses": 11104.0,
        "totalClearances": 822.0,
        "goalsConceded": 43.0,
        "groundDuelsLost": 895.0,
        "duels": 2664.0,
        "putthroughBlockedDistributionWon": 185.0,
        "homeGoals": 24.0,
        "possessionPercentage": 51.7,
        "oboxTarget": 24.0,
        "drops": 1.0,
        "tacklesLost": 211.0,
        "lastPlayerTackle": 7.0,
        "successfulPassesOppositionHalf": 5196.0,
        "goalsConcededInsideBox": 39.0,
        "headedGoals": 7.0,
        "iboxBlocked": 70.0,
        "groundDuels": 1815.0,
        "aerialDuelsWon": 415.0,
        "straightRedCards": 0.0,
        "cornersWon": 137.0,
        "successfulDribbles": 172.0,
        "blocks": 104.0,
        "gkUnsuccessfulDistribution": 75.0,
        "interceptions": 242.0,
        "penaltyGoals": 3.0,
        "unsuccessfulLaunches": 408.0,
        "foulAttemptedTackle": 131.0,
        "shotsOnConcededOutsideBox": 27.0,
        "goalConversion": 16.26,
        "expectedGoals": 36.0775,
        "yellowCards": 60.0
      }
    },
    {
      "teamMetadata": {
        "name": "Sunderland",
        "season": "2025",
        "id": "56",
        "shortName": "Sunderland",
        "abbr": "SUN"
      },
      "stats": {
        "duelsLost": 1418.0,
        "penaltiesSaved": 1.0,
        "blockedShots": 77.0,
        "shotsOnTargetIncGoals": 91.0,
        "expectedGoalsOnTarget": 27.4062,
        "gamesPlayed": 29.0,
        "crossingAccuracy": 19.91,
        "totalPasses": 10706.0,
        "goals": 30.0,
        "offsides": 44.0,
        "awayGoals": 8.0,
        "tackleSuccess": 58.79,
        "oboxBlocked": 20.0,
        "passingAccuracy": 78.82,
        "iboxTarget": 48.0,
        "aerialDuelsLost": 546.0,
        "goalsConcededOutsideBox": 6.0,
        "ownGoalsAccrued": 3.0,
        "groundDuelsWon": 900.0,
        "successfulCornersIntoBox": 25.0,
        "penaltyGoalsConceded": 2.0,
        "expectedGoalsOnTargetConceded": 34.9421,
        "keyPassesAttemptAssists": 172.0,
        "successfulLaunches": 140.0,
        "totalFoulsWon": 303.0,
        "recoveries": 1279.0,
        "pointsGainedFromLosingPositions": 16.0,
        "passingPercentOppHalf": 69.28,
        "shotsOnConcededInsideBox": 90.0,
        "rightFootGoals": 17.0,
        "leftFootGoals": 4.0,
        "unsuccessfulDribbles": 198.0,
        "unsuccessfulCrossesAndCorners": 354.0,
        "timesTackled": 411.0,
        "freekickTotal": 4.0,
        "openPlayPasses": 10060.0,
        "gkSuccessfulDistribution": 256.0,
        "shotsOffTargetIncWoodwork": 107.0,
        "totalLossesOfPossession": 3710.0,
        "tacklesWon": 271.0,
        "attemptsFromSetPieces": 4.0,
        "totalShotsConceded": 427.0,
        "totalFoulsConceded": 296.0,
        "unsuccessfulCornersIntoBox": 63.0,
        "successfulLongPasses": 588.0,
        "clearancesOffTheLine": 4.0,
        "throwInsToOwnPlayer": 341.0,
        "touchesInOppBox": 544.0,
        "hitWoodwork": 10.0,
        "successfulPassesOwnHalf": 4574.0,
        "pointsDroppedFromWinningPositions": 8.0,
        "ownGoalsConceded": 1.0,
        "handballsConceded": 11.0,
        "unsuccessfulLongPasses": 959.0,
        "unsuccessfulPassesOwnHalf": 555.0,
        "successfulCrossesOpenPlay": 57.0,
        "expectedAssists": 15.4969,
        "totalRedCards": 2.0,
        "expectedGoalsFreekick": 0.1652,
        "catches": 42.0,
        "overruns": 42.0,
        "unsuccessfulPassesOppositionHalf": 2067.0,
        "totalShots": 198.0,
        "unsuccessfulShortPasses": 1309.0,
        "goalAssists": 18.0,
        "successfulLayoffs": 195.0,
        "foulWonPenalty": 5.0,
        "unsuccessfulCrossesOpenPlay": 264.0,
        "goalKicks": 239.0,
        "cornersTakenInclShortCorners": 100.0,
        "aerialDuels": 1091.0,
        "cleanSheets": 9.0,
        "shootingAccuracy": 45.96,
        "successfulCrossesAndCorners": 88.0,
        "unsuccessfulLayoffs": 16.0,
        "duelsWon": 1445.0,
        "penaltiesConceded": 3.0,
        "putthroughBlockedDistribution": 445.0,
        "successfulShortPasses": 7850.0,
        "throwInsToOppositionPlayer": 169.0,
        "successfulOpenPlayPasses": 8031.0,
        "totalClearances": 946.0,
        "goalsConceded": 34.0,
        "groundDuelsLost": 872.0,
        "duels": 2863.0,
        "putthroughBlockedDistributionWon": 195.0,
        "homeGoals": 22.0,
        "possessionPercentage": 43.7,
        "oboxTarget": 16.0,
        "drops": 4.0,
        "tacklesLost": 190.0,
        "lastPlayerTackle": 8.0,
        "successfulPassesOppositionHalf": 3952.0,
        "goalsConcededInsideBox": 28.0,
        "headedGoals": 6.0,
        "iboxBlocked": 57.0,
        "groundDuels": 1772.0,
        "aerialDuelsWon": 545.0,
        "straightRedCards": 2.0,
        "cornersWon": 100.0,
        "successfulDribbles": 153.0,
        "blocks": 130.0,
        "gkUnsuccessfulDistribution": 108.0,
        "interceptions": 233.0,
        "penaltyGoals": 4.0,
        "unsuccessfulLaunches": 522.0,
        "foulAttemptedTackle": 146.0,
        "shotsOnConcededOutsideBox": 37.0,
        "goalConversion": 15.15,
        "expectedGoals": 26.9699,
        "yellowCards": 58.0
      }
    },
    {
      "teamMetadata": {
        "name": "Tottenham Hotspur",
        "season": "2025",
        "id": "6",
        "shortName": "Spurs",
        "abbr": "TOT"
      },
      "stats": {
        "duelsLost": 1604.0,
        "blockedShots": 94.0,
        "shotsOnTargetIncGoals": 108.0,
        "expectedGoalsOnTarget": 39.5743,
        "gamesPlayed": 29.0,
        "crossingAccuracy": 22.77,
        "totalPasses": 11951.0,
        "goals": 39.0,
        "offsides": 45.0,
        "awayGoals": 21.0,
        "tackleSuccess": 60.84,
        "redCard2ndYellow": 1.0,
        "oboxBlocked": 33.0,
        "passingAccuracy": 81.34,
        "iboxTarget": 49.0,
        "aerialDuelsLost": 515.0,
        "goalsConcededOutsideBox": 10.0,
        "ownGoalsAccrued": 1.0,
        "groundDuelsWon": 1111.0,
        "successfulCornersIntoBox": 32.0,
        "penaltyGoalsConceded": 2.0,
        "expectedGoalsOnTargetConceded": 41.4238,
        "keyPassesAttemptAssists": 205.0,
        "successfulLaunches": 94.0,
        "totalFoulsWon": 277.0,
        "recoveries": 1452.0,
        "pointsGainedFromLosingPositions": 6.0,
        "passingPercentOppHalf": 74.09,
        "shotsOnConcededInsideBox": 94.0,
        "rightFootGoals": 21.0,
        "leftFootGoals": 6.0,
        "unsuccessfulDribbles": 287.0,
        "unsuccessfulCrossesAndCorners": 458.0,
        "timesTackled": 584.0,
        "freekickTotal": 9.0,
        "openPlayPasses": 11300.0,
        "gkSuccessfulDistribution": 293.0,
        "shotsOffTargetIncWoodwork": 117.0,
        "totalLossesOfPossession": 4009.0,
        "tacklesWon": 348.0,
        "attemptsFromSetPieces": 9.0,
        "totalShotsConceded": 373.0,
        "totalFoulsConceded": 336.0,
        "unsuccessfulCornersIntoBox": 97.0,
        "successfulLongPasses": 579.0,
        "clearancesOffTheLine": 2.0,
        "throwInsToOwnPlayer": 443.0,
        "touchesInOppBox": 691.0,
        "hitWoodwork": 6.0,
        "successfulPassesOwnHalf": 5206.0,
        "pointsDroppedFromWinningPositions": 15.0,
        "handballsConceded": 7.0,
        "unsuccessfulLongPasses": 858.0,
        "unsuccessfulPassesOwnHalf": 651.0,
        "successfulCrossesOpenPlay": 95.0,
        "expectedAssists": 22.4139,
        "totalRedCards": 4.0,
        "expectedGoalsFreekick": 0.6001,
        "catches": 21.0,
        "overruns": 38.0,
        "unsuccessfulPassesOppositionHalf": 2037.0,
        "totalShots": 225.0,
        "unsuccessfulShortPasses": 1372.0,
        "goalAssists": 30.0,
        "successfulLayoffs": 162.0,
        "unsuccessfulCrossesOpenPlay": 344.0,
        "goalKicks": 234.0,
        "cornersTakenInclShortCorners": 144.0,
        "aerialDuels": 945.0,
        "cleanSheets": 7.0,
        "shootingAccuracy": 48.0,
        "successfulCrossesAndCorners": 135.0,
        "unsuccessfulLayoffs": 18.0,
        "duelsWon": 1541.0,
        "penaltiesConceded": 2.0,
        "putthroughBlockedDistribution": 506.0,
        "successfulShortPasses": 9142.0,
        "throwInsToOppositionPlayer": 132.0,
        "successfulOpenPlayPasses": 9219.0,
        "totalClearances": 791.0,
        "goalsConceded": 46.0,
        "groundDuelsLost": 1089.0,
        "duels": 3145.0,
        "putthroughBlockedDistributionWon": 234.0,
        "homeGoals": 18.0,
        "possessionPercentage": 49.8,
        "oboxTarget": 21.0,
        "drops": 1.0,
        "tacklesLost": 224.0,
        "lastPlayerTackle": 10.0,
        "successfulPassesOppositionHalf": 4650.0,
        "goalsConcededInsideBox": 36.0,
        "headedGoals": 11.0,
        "iboxBlocked": 61.0,
        "groundDuels": 2200.0,
        "aerialDuelsWon": 430.0,
        "straightRedCards": 3.0,
        "cornersWon": 144.0,
        "successfulDribbles": 264.0,
        "blocks": 100.0,
        "gkUnsuccessfulDistribution": 65.0,
        "interceptions": 224.0,
        "unsuccessfulLaunches": 469.0,
        "foulAttemptedTackle": 180.0,
        "shotsOnConcededOutsideBox": 30.0,
        "goalConversion": 17.33,
        "expectedGoals": 30.1345,
        "yellowCards": 74.0
      }
    },
    {
      "teamMetadata": {
        "name": "Aston Villa",
        "season": "2025",
        "id": "7",
        "shortName": "Aston Villa",
        "abbr": "AVL"
      },
      "stats": {
        "duelsLost": 1397.0,
        "penaltiesSaved": 1.0,
        "blockedShots": 115.0,
        "shotsOnTargetIncGoals": 126.0,
        "expectedGoalsOnTarget": 35.5954,
        "gamesPlayed": 29.0,
        "setPiecesGoals": 2.0,
        "crossingAccuracy": 21.98,
        "totalPasses": 13041.0,
        "goals": 39.0,
        "offsides": 33.0,
        "awayGoals": 18.0,
        "tackleSuccess": 57.66,
        "oboxBlocked": 40.0,
        "passingAccuracy": 84.99,
        "iboxTarget": 57.0,
        "aerialDuelsLost": 351.0,
        "goalsConcededOutsideBox": 4.0,
        "ownGoalsAccrued": 2.0,
        "groundDuelsWon": 983.0,
        "successfulCornersIntoBox": 39.0,
        "penaltyGoalsConceded": 1.0,
        "expectedGoalsOnTargetConceded": 37.4722,
        "keyPassesAttemptAssists": 248.0,
        "successfulLaunches": 96.0,
        "totalFoulsWon": 371.0,
        "recoveries": 1293.0,
        "pointsGainedFromLosingPositions": 19.0,
        "passingPercentOppHalf": 78.81,
        "shotsOnConcededInsideBox": 85.0,
        "rightFootGoals": 24.0,
        "leftFootGoals": 9.0,
        "unsuccessfulDribbles": 257.0,
        "unsuccessfulCrossesAndCorners": 362.0,
        "timesTackled": 560.0,
        "freekickTotal": 11.0,
        "openPlayPasses": 12210.0,
        "gkSuccessfulDistribution": 313.0,
        "shotsOffTargetIncWoodwork": 124.0,
        "totalLossesOfPossession": 3499.0,
        "tacklesWon": 256.0,
        "attemptsFromSetPieces": 11.0,
        "totalShotsConceded": 370.0,
        "totalFoulsConceded": 302.0,
        "unsuccessfulCornersIntoBox": 68.0,
        "successfulLongPasses": 572.0,
        "clearancesOffTheLine": 7.0,
        "throwInsToOwnPlayer": 340.0,
        "touchesInOppBox": 772.0,
        "hitWoodwork": 11.0,
        "successfulPassesOwnHalf": 5756.0,
        "pointsDroppedFromWinningPositions": 7.0,
        "ownGoalsConceded": 1.0,
        "handballsConceded": 1.0,
        "unsuccessfulLongPasses": 673.0,
        "unsuccessfulPassesOwnHalf": 526.0,
        "successfulCrossesOpenPlay": 61.0,
        "expectedAssists": 24.7789,
        "totalRedCards": 1.0,
        "expectedGoalsFreekick": 0.8278,
        "catches": 45.0,
        "overruns": 31.0,
        "unsuccessfulPassesOppositionHalf": 1794.0,
        "totalShots": 250.0,
        "unsuccessfulShortPasses": 1285.0,
        "goalAssists": 28.0,
        "successfulLayoffs": 218.0,
        "unsuccessfulCrossesOpenPlay": 272.0,
        "goalKicks": 238.0,
        "cornersTakenInclShortCorners": 154.0,
        "aerialDuels": 730.0,
        "cleanSheets": 8.0,
        "shootingAccuracy": 50.4,
        "successfulCrossesAndCorners": 102.0,
        "unsuccessfulLayoffs": 30.0,
        "duelsWon": 1362.0,
        "penaltiesConceded": 2.0,
        "putthroughBlockedDistribution": 453.0,
        "successfulShortPasses": 10511.0,
        "throwInsToOppositionPlayer": 111.0,
        "successfulOpenPlayPasses": 10394.0,
        "totalClearances": 621.0,
        "goalsConceded": 34.0,
        "groundDuelsLost": 1046.0,
        "duels": 2759.0,
        "putthroughBlockedDistributionWon": 195.0,
        "homeGoals": 21.0,
        "possessionPercentage": 53.5,
        "oboxTarget": 32.0,
        "drops": 4.0,
        "tacklesLost": 188.0,
        "lastPlayerTackle": 1.0,
        "successfulPassesOppositionHalf": 5429.0,
        "goalsConcededInsideBox": 30.0,
        "headedGoals": 4.0,
        "iboxBlocked": 75.0,
        "groundDuels": 2029.0,
        "aerialDuelsWon": 379.0,
        "straightRedCards": 1.0,
        "cornersWon": 154.0,
        "successfulDribbles": 184.0,
        "blocks": 114.0,
        "gkUnsuccessfulDistribution": 43.0,
        "interceptions": 181.0,
        "unsuccessfulLaunches": 265.0,
        "foulAttemptedTackle": 153.0,
        "shotsOnConcededOutsideBox": 40.0,
        "goalConversion": 15.6,
        "expectedGoals": 35.2814,
        "yellowCards": 45.0
      }
    },
    {
      "teamMetadata": {
        "name": "Chelsea",
        "season": "2025",
        "id": "8",
        "shortName": "Chelsea",
        "abbr": "CHE"
      },
      "stats": {
        "duelsLost": 1342.0,
        "blockedShots": 118.0,
        "shotsOnTargetIncGoals": 138.0,
        "expectedGoalsOnTarget": 56.4238,
        "gamesPlayed": 29.0,
        "setPiecesGoals": 2.0,
        "crossingAccuracy": 20.46,
        "totalPasses": 15625.0,
        "goals": 53.0,
        "offsides": 41.0,
        "awayGoals": 30.0,
        "tackleSuccess": 58.33,
        "redCard2ndYellow": 3.0,
        "oboxBlocked": 38.0,
        "passingAccuracy": 87.08,
        "iboxTarget": 55.0,
        "aerialDuelsLost": 380.0,
        "goalsConcededOutsideBox": 3.0,
        "ownGoalsAccrued": 1.0,
        "groundDuelsWon": 1006.0,
        "successfulCornersIntoBox": 34.0,
        "penaltyGoalsConceded": 1.0,
        "expectedGoalsOnTargetConceded": 36.1856,
        "keyPassesAttemptAssists": 256.0,
        "successfulLaunches": 126.0,
        "totalFoulsWon": 331.0,
        "recoveries": 1356.0,
        "pointsGainedFromLosingPositions": 13.0,
        "passingPercentOppHalf": 81.29,
        "shotsOnConcededInsideBox": 90.0,
        "rightFootGoals": 20.0,
        "leftFootGoals": 22.0,
        "unsuccessfulDribbles": 248.0,
        "unsuccessfulCrossesAndCorners": 412.0,
        "timesTackled": 478.0,
        "freekickTotal": 13.0,
        "openPlayPasses": 14954.0,
        "gkSuccessfulDistribution": 273.0,
        "shotsOffTargetIncWoodwork": 136.0,
        "totalLossesOfPossession": 3493.0,
        "tacklesWon": 273.0,
        "attemptsFromSetPieces": 13.0,
        "totalShotsConceded": 317.0,
        "totalFoulsConceded": 324.0,
        "unsuccessfulCornersIntoBox": 101.0,
        "successfulLongPasses": 625.0,
        "clearancesOffTheLine": 2.0,
        "throwInsToOwnPlayer": 410.0,
        "touchesInOppBox": 785.0,
        "hitWoodwork": 11.0,
        "successfulPassesOwnHalf": 7369.0,
        "pointsDroppedFromWinningPositions": 19.0,
        "handballsConceded": 9.0,
        "unsuccessfulLongPasses": 743.0,
        "unsuccessfulPassesOwnHalf": 583.0,
        "successfulCrossesOpenPlay": 70.0,
        "expectedAssists": 34.4466,
        "totalRedCards": 7.0,
        "expectedGoalsFreekick": 0.689,
        "catches": 36.0,
        "overruns": 24.0,
        "unsuccessfulPassesOppositionHalf": 1848.0,
        "totalShots": 274.0,
        "unsuccessfulShortPasses": 1276.0,
        "goalAssists": 35.0,
        "successfulLayoffs": 345.0,
        "foulWonPenalty": 7.0,
        "unsuccessfulCrossesOpenPlay": 291.0,
        "goalKicks": 192.0,
        "cornersTakenInclShortCorners": 176.0,
        "aerialDuels": 790.0,
        "cleanSheets": 9.0,
        "shootingAccuracy": 50.36,
        "successfulCrossesAndCorners": 106.0,
        "unsuccessfulLayoffs": 30.0,
        "duelsWon": 1416.0,
        "penaltiesConceded": 1.0,
        "putthroughBlockedDistribution": 415.0,
        "successfulShortPasses": 12981.0,
        "throwInsToOppositionPlayer": 43.0,
        "successfulOpenPlayPasses": 13062.0,
        "totalClearances": 673.0,
        "goalsConceded": 34.0,
        "groundDuelsLost": 962.0,
        "duels": 2758.0,
        "putthroughBlockedDistributionWon": 190.0,
        "homeGoals": 23.0,
        "possessionPercentage": 58.5,
        "oboxTarget": 31.0,
        "drops": 2.0,
        "tacklesLost": 195.0,
        "lastPlayerTackle": 8.0,
        "successfulPassesOppositionHalf": 6343.0,
        "goalsConcededInsideBox": 31.0,
        "headedGoals": 10.0,
        "iboxBlocked": 80.0,
        "groundDuels": 1968.0,
        "aerialDuelsWon": 410.0,
        "straightRedCards": 4.0,
        "cornersWon": 176.0,
        "successfulDribbles": 212.0,
        "blocks": 82.0,
        "gkUnsuccessfulDistribution": 61.0,
        "interceptions": 292.0,
        "penaltyGoals": 7.0,
        "unsuccessfulLaunches": 355.0,
        "foulAttemptedTackle": 172.0,
        "shotsOnConcededOutsideBox": 22.0,
        "goalConversion": 19.34,
        "expectedGoals": 56.9752,
        "yellowCards": 67.0
      }
    },
    {
      "teamMetadata": {
        "name": "Burnley",
        "season": "2025",
        "id": "90",
        "shortName": "Burnley",
        "abbr": "BUR"
      },
      "stats": {
        "duelsLost": 1501.0,
        "blockedShots": 83.0,
        "shotsOnTargetIncGoals": 85.0,
        "expectedGoalsOnTarget": 26.4964,
        "gamesPlayed": 29.0,
        "crossingAccuracy": 18.73,
        "totalPasses": 10973.0,
        "goals": 32.0,
        "offsides": 48.0,
        "awayGoals": 17.0,
        "tackleSuccess": 57.76,
        "redCard2ndYellow": 1.0,
        "oboxBlocked": 34.0,
        "passingAccuracy": 78.47,
        "iboxTarget": 33.0,
        "aerialDuelsLost": 550.0,
        "goalsConcededOutsideBox": 4.0,
        "ownGoalsAccrued": 3.0,
        "groundDuelsWon": 875.0,
        "successfulCornersIntoBox": 17.0,
        "penaltyGoalsConceded": 5.0,
        "expectedGoalsOnTargetConceded": 54.6323,
        "keyPassesAttemptAssists": 168.0,
        "successfulLaunches": 145.0,
        "totalFoulsWon": 256.0,
        "recoveries": 1293.0,
        "pointsGainedFromLosingPositions": 9.0,
        "passingPercentOppHalf": 69.59,
        "shotsOnConcededInsideBox": 133.0,
        "rightFootGoals": 12.0,
        "leftFootGoals": 11.0,
        "unsuccessfulDribbles": 204.0,
        "unsuccessfulCrossesAndCorners": 308.0,
        "timesTackled": 445.0,
        "freekickTotal": 13.0,
        "openPlayPasses": 10277.0,
        "gkSuccessfulDistribution": 244.0,
        "shotsOffTargetIncWoodwork": 95.0,
        "totalLossesOfPossession": 3803.0,
        "tacklesWon": 283.0,
        "attemptsFromSetPieces": 13.0,
        "totalShotsConceded": 476.0,
        "totalFoulsConceded": 290.0,
        "unsuccessfulCornersIntoBox": 69.0,
        "successfulLongPasses": 596.0,
        "clearancesOffTheLine": 8.0,
        "throwInsToOwnPlayer": 360.0,
        "touchesInOppBox": 483.0,
        "hitWoodwork": 8.0,
        "successfulPassesOwnHalf": 4504.0,
        "pointsDroppedFromWinningPositions": 7.0,
        "ownGoalsConceded": 4.0,
        "handballsConceded": 12.0,
        "unsuccessfulLongPasses": 1006.0,
        "unsuccessfulPassesOwnHalf": 567.0,
        "successfulCrossesOpenPlay": 50.0,
        "expectedAssists": 15.4532,
        "totalRedCards": 2.0,
        "expectedGoalsFreekick": 0.7158,
        "catches": 17.0,
        "overruns": 32.0,
        "unsuccessfulPassesOppositionHalf": 2103.0,
        "totalShots": 180.0,
        "unsuccessfulShortPasses": 1356.0,
        "goalAssists": 22.0,
        "successfulLayoffs": 195.0,
        "foulWonPenalty": 2.0,
        "unsuccessfulCrossesOpenPlay": 219.0,
        "goalKicks": 303.0,
        "cornersTakenInclShortCorners": 100.0,
        "aerialDuels": 1010.0,
        "cleanSheets": 3.0,
        "shootingAccuracy": 47.22,
        "successfulCrossesAndCorners": 71.0,
        "unsuccessfulLayoffs": 22.0,
        "duelsWon": 1335.0,
        "penaltiesConceded": 6.0,
        "putthroughBlockedDistribution": 485.0,
        "successfulShortPasses": 8015.0,
        "throwInsToOppositionPlayer": 167.0,
        "successfulOpenPlayPasses": 8228.0,
        "totalClearances": 891.0,
        "goalsConceded": 58.0,
        "groundDuelsLost": 951.0,
        "duels": 2836.0,
        "putthroughBlockedDistributionWon": 237.0,
        "homeGoals": 15.0,
        "possessionPercentage": 41.7,
        "oboxTarget": 23.0,
        "drops": 1.0,
        "tacklesLost": 207.0,
        "lastPlayerTackle": 3.0,
        "successfulPassesOppositionHalf": 4178.0,
        "goalsConcededInsideBox": 54.0,
        "headedGoals": 6.0,
        "iboxBlocked": 49.0,
        "groundDuels": 1826.0,
        "aerialDuelsWon": 460.0,
        "straightRedCards": 1.0,
        "cornersWon": 100.0,
        "successfulDribbles": 141.0,
        "blocks": 132.0,
        "gkUnsuccessfulDistribution": 178.0,
        "interceptions": 267.0,
        "penaltyGoals": 2.0,
        "unsuccessfulLaunches": 465.0,
        "foulAttemptedTackle": 138.0,
        "shotsOnConcededOutsideBox": 37.0,
        "goalConversion": 17.78,
        "expectedGoals": 24.4794,
        "yellowCards": 48.0
      }
    },
    {
      "teamMetadata": {
        "name": "Bournemouth",
        "season": "2025",
        "id": "91",
        "shortName": "Bournemouth",
        "abbr": "BOU"
      },
      "stats": {
        "duelsLost": 1631.0,
        "blockedShots": 110.0,
        "shotsOnTargetIncGoals": 140.0,
        "expectedGoalsOnTarget": 42.1877,
        "gamesPlayed": 29.0,
        "setPiecesGoals": 2.0,
        "crossingAccuracy": 16.55,
        "totalPasses": 11847.0,
        "goals": 44.0,
        "offsides": 59.0,
        "awayGoals": 23.0,
        "tackleSuccess": 58.12,
        "oboxBlocked": 53.0,
        "passingAccuracy": 79.65,
        "iboxTarget": 63.0,
        "aerialDuelsLost": 562.0,
        "goalsConcededOutsideBox": 7.0,
        "groundDuelsWon": 999.0,
        "successfulCornersIntoBox": 16.0,
        "penaltyGoalsConceded": 4.0,
        "expectedGoalsOnTargetConceded": 44.5729,
        "keyPassesAttemptAssists": 243.0,
        "successfulLaunches": 132.0,
        "totalFoulsWon": 291.0,
        "recoveries": 1490.0,
        "pointsGainedFromLosingPositions": 15.0,
        "passingPercentOppHalf": 72.59,
        "shotsOnConcededInsideBox": 94.0,
        "rightFootGoals": 20.0,
        "leftFootGoals": 19.0,
        "unsuccessfulDribbles": 273.0,
        "unsuccessfulCrossesAndCorners": 479.0,
        "timesTackled": 519.0,
        "freekickTotal": 16.0,
        "openPlayPasses": 11223.0,
        "gkSuccessfulDistribution": 295.0,
        "shotsOffTargetIncWoodwork": 146.0,
        "totalLossesOfPossession": 4072.0,
        "tacklesWon": 290.0,
        "attemptsFromSetPieces": 16.0,
        "totalShotsConceded": 364.0,
        "totalFoulsConceded": 352.0,
        "unsuccessfulCornersIntoBox": 110.0,
        "successfulLongPasses": 597.0,
        "clearancesOffTheLine": 2.0,
        "throwInsToOwnPlayer": 428.0,
        "touchesInOppBox": 713.0,
        "hitWoodwork": 12.0,
        "successfulPassesOwnHalf": 4496.0,
        "pointsDroppedFromWinningPositions": 18.0,
        "ownGoalsConceded": 1.0,
        "handballsConceded": 10.0,
        "unsuccessfulLongPasses": 956.0,
        "unsuccessfulPassesOwnHalf": 546.0,
        "successfulCrossesOpenPlay": 74.0,
        "expectedAssists": 25.6837,
        "totalRedCards": 1.0,
        "expectedGoalsFreekick": 1.2607,
        "catches": 23.0,
        "overruns": 25.0,
        "unsuccessfulPassesOppositionHalf": 2344.0,
        "totalShots": 286.0,
        "unsuccessfulShortPasses": 1455.0,
        "goalAssists": 26.0,
        "successfulLayoffs": 199.0,
        "foulWonPenalty": 4.0,
        "unsuccessfulCrossesOpenPlay": 339.0,
        "goalKicks": 225.0,
        "cornersTakenInclShortCorners": 163.0,
        "aerialDuels": 1039.0,
        "cleanSheets": 8.0,
        "shootingAccuracy": 48.95,
        "successfulCrossesAndCorners": 95.0,
        "unsuccessfulLayoffs": 20.0,
        "duelsWon": 1476.0,
        "penaltiesConceded": 4.0,
        "putthroughBlockedDistribution": 489.0,
        "successfulShortPasses": 8839.0,
        "throwInsToOppositionPlayer": 127.0,
        "successfulOpenPlayPasses": 8964.0,
        "totalClearances": 915.0,
        "goalsConceded": 46.0,
        "groundDuelsLost": 1069.0,
        "duels": 3107.0,
        "putthroughBlockedDistributionWon": 235.0,
        "homeGoals": 21.0,
        "possessionPercentage": 49.8,
        "oboxTarget": 33.0,
        "drops": 7.0,
        "tacklesLost": 209.0,
        "lastPlayerTackle": 10.0,
        "successfulPassesOppositionHalf": 5035.0,
        "goalsConcededInsideBox": 39.0,
        "headedGoals": 5.0,
        "iboxBlocked": 57.0,
        "groundDuels": 2068.0,
        "aerialDuelsWon": 477.0,
        "straightRedCards": 1.0,
        "cornersWon": 163.0,
        "successfulDribbles": 218.0,
        "blocks": 108.0,
        "gkUnsuccessfulDistribution": 70.0,
        "interceptions": 284.0,
        "penaltyGoals": 3.0,
        "unsuccessfulLaunches": 523.0,
        "foulAttemptedTackle": 163.0,
        "shotsOnConcededOutsideBox": 40.0,
        "goalConversion": 15.38,
        "expectedGoals": 45.6217,
        "yellowCards": 69.0
      }
    },
    {
      "teamMetadata": {
        "name": "Brentford",
        "season": "2025",
        "id": "94",
        "shortName": "Brentford",
        "abbr": "BRE"
      },
      "stats": {
        "duelsLost": 1533.0,
        "penaltiesSaved": 3.0,
        "blockedShots": 72.0,
        "shotsOnTargetIncGoals": 117.0,
        "expectedGoalsOnTarget": 44.2769,
        "gamesPlayed": 29.0,
        "crossingAccuracy": 25.49,
        "totalPasses": 11413.0,
        "goals": 44.0,
        "offsides": 48.0,
        "awayGoals": 20.0,
        "tackleSuccess": 58.16,
        "oboxBlocked": 26.0,
        "passingAccuracy": 79.31,
        "iboxTarget": 59.0,
        "aerialDuelsLost": 541.0,
        "goalsConcededOutsideBox": 2.0,
        "ownGoalsAccrued": 1.0,
        "groundDuelsWon": 865.0,
        "successfulCornersIntoBox": 40.0,
        "penaltyGoalsConceded": 4.0,
        "expectedGoalsOnTargetConceded": 35.5537,
        "keyPassesAttemptAssists": 193.0,
        "successfulLaunches": 200.0,
        "totalFoulsWon": 265.0,
        "recoveries": 1453.0,
        "pointsGainedFromLosingPositions": 8.0,
        "passingPercentOppHalf": 68.47,
        "shotsOnConcededInsideBox": 86.0,
        "rightFootGoals": 22.0,
        "leftFootGoals": 13.0,
        "unsuccessfulDribbles": 260.0,
        "unsuccessfulCrossesAndCorners": 383.0,
        "timesTackled": 495.0,
        "freekickTotal": 7.0,
        "openPlayPasses": 10841.0,
        "gkSuccessfulDistribution": 244.0,
        "shotsOffTargetIncWoodwork": 115.0,
        "totalLossesOfPossession": 3969.0,
        "tacklesWon": 246.0,
        "attemptsFromSetPieces": 7.0,
        "totalShotsConceded": 364.0,
        "totalFoulsConceded": 308.0,
        "unsuccessfulCornersIntoBox": 90.0,
        "successfulLongPasses": 689.0,
        "clearancesOffTheLine": 4.0,
        "throwInsToOwnPlayer": 374.0,
        "touchesInOppBox": 716.0,
        "hitWoodwork": 10.0,
        "successfulPassesOwnHalf": 5147.0,
        "pointsDroppedFromWinningPositions": 13.0,
        "ownGoalsConceded": 3.0,
        "handballsConceded": 7.0,
        "unsuccessfulLongPasses": 969.0,
        "unsuccessfulPassesOwnHalf": 563.0,
        "successfulCrossesOpenPlay": 75.0,
        "expectedAssists": 26.1592,
        "totalRedCards": 1.0,
        "expectedGoalsFreekick": 0.4966,
        "catches": 16.0,
        "overruns": 33.0,
        "unsuccessfulPassesOppositionHalf": 2181.0,
        "totalShots": 232.0,
        "unsuccessfulShortPasses": 1392.0,
        "goalAssists": 27.0,
        "successfulLayoffs": 185.0,
        "foulWonPenalty": 8.0,
        "unsuccessfulCrossesOpenPlay": 268.0,
        "goalKicks": 213.0,
        "cornersTakenInclShortCorners": 145.0,
        "aerialDuels": 1106.0,
        "cleanSheets": 7.0,
        "shootingAccuracy": 50.43,
        "successfulCrossesAndCorners": 131.0,
        "unsuccessfulLayoffs": 20.0,
        "duelsWon": 1430.0,
        "penaltiesConceded": 7.0,
        "putthroughBlockedDistribution": 379.0,
        "successfulShortPasses": 8363.0,
        "throwInsToOppositionPlayer": 188.0,
        "successfulOpenPlayPasses": 8667.0,
        "totalClearances": 856.0,
        "goalsConceded": 40.0,
        "groundDuelsLost": 992.0,
        "duels": 2963.0,
        "putthroughBlockedDistributionWon": 197.0,
        "homeGoals": 24.0,
        "possessionPercentage": 47.1,
        "oboxTarget": 15.0,
        "drops": 4.0,
        "tacklesLost": 177.0,
        "lastPlayerTackle": 3.0,
        "successfulPassesOppositionHalf": 4036.0,
        "goalsConcededInsideBox": 38.0,
        "headedGoals": 8.0,
        "iboxBlocked": 46.0,
        "groundDuels": 1857.0,
        "aerialDuelsWon": 565.0,
        "straightRedCards": 1.0,
        "cornersWon": 145.0,
        "successfulDribbles": 185.0,
        "blocks": 121.0,
        "gkUnsuccessfulDistribution": 91.0,
        "interceptions": 261.0,
        "penaltyGoals": 6.0,
        "unsuccessfulLaunches": 538.0,
        "foulAttemptedTackle": 124.0,
        "shotsOnConcededOutsideBox": 32.0,
        "goalConversion": 18.97,
        "expectedGoals": 45.9959,
        "yellowCards": 56.0
      }
    }
  ]
}
