{
  "pagination": {
    "_limit": 20,
    "_prev": null,
    "_next": null
  },
  "data": [
    {
      "teamMetadata": {
        "name": "Manchester United",
        "season": "2025",
        "id": "1",
        "shortName": "Man Utd",
        "abbr": "MUN"
      },
      "stats": {
        "duelsLost": 245.0,
        "blockedShots": 22.0,
        "shotsOnTargetIncGoals": 22.0,
        "expectedGoalsOnTarget": 5.4852,
        "gamesPlayed": 5.0,
        "crossingAccuracy": 32.69,
        "totalPasses": 2252.0,
        "goals": 6.0,
        "offsides": 9.0,
        "awayGoals": 1.0,
        "tackleSuccess": 62.63,
        "redCard2ndYellow": 1.0,
        "oboxBlocked": 10.0,
        "passingAccuracy": 82.19,
        "iboxTarget": 12.0,
        "aerialDuelsLost": 92.0,
        "ownGoalsAccrued": 2.0,
        "groundDuelsWon": 182.0,
        "successfulCornersIntoBox": 8.0,
        "expectedGoalsOnTargetConceded": 7.1359,
        "keyPassesAttemptAssists": 57.0,
        "successfulLaunches": 22.0,
        "totalFoulsWon": 60.0,
        "recoveries": 226.0,
        "passingPercentOppHalf": 76.84,
        "shotsOnConcededInsideBox": 15.0,
        "rightFootGoals": 2.0,
        "leftFootGoals": 1.0,
        "unsuccessfulDribbles": 31.0,
        "unsuccessfulCrossesAndCorners": 70.0,
        "timesTackled": 77.0,
        "freekickTotal": 2.0,
        "openPlayPasses": 2155.0,
        "gkSuccessfulDistribution": 30.0,
        "shotsOffTargetIncWoodwork": 37.0,
        "totalLossesOfPossession": 656.0,
        "tacklesWon": 62.0,
        "attemptsFromSetPieces": 2.0,
        "totalShotsConceded": 46.0,
        "totalFoulsConceded": 50.0,
        "unsuccessfulCornersIntoBox": 14.0,
        "successfulLongPasses": 144.0,
        "clearancesOffTheLine": 1.0,
        "throwInsToOwnPlayer": 81.0,
        "touchesInOppBox": 149.0,
        "hitWoodwork": 4.0,
        "successfulPassesOwnHalf": 912.0,
        "pointsDroppedFromWinningPositions": 2.0,
        "handballsConceded": 1.0,
        "unsuccessfulLongPasses": 147.0,
        "unsuccessfulPassesOwnHalf": 118.0,
        "successfulCrossesOpenPlay": 25.0,
        "expectedAssists": 5.9873,
        "totalRedCards": 1.0,
        "expectedGoalsFreekick": 0.2308,
        "catches": 3.0,
        "overruns": 8.0,
        "unsuccessfulPassesOppositionHalf": 353.0,
        "totalShots": 59.0,
        "unsuccessfulShortPasses": 254.0,
        "goalAssists": 3.0,
        "successfulLayoffs": 50.0,
        "foulWonPenalty": 2.0,
        "unsuccessfulCrossesOpenPlay": 46.0,
        "goalKicks": 25.0,
        "cornersTakenInclShortCorners": 25.0,
        "aerialDuels": 182.0,
        "shootingAccuracy": 37.29,
        "successfulCrossesAndCorners": 34.0,
        "unsuccessfulLayoffs": 6.0,
        "duelsWon": 272.0,
        "putthroughBlockedDistribution": 77.0,
        "successfulShortPasses": 1707.0,
        "throwInsToOppositionPlayer": 21.0,
        "successfulOpenPlayPasses": 1773.0,
        "totalClearances": 96.0,
        "goalsConceded": 8.0,
        "groundDuelsLost": 153.0,
        "duels": 517.0,
        "putthroughBlockedDistributionWon": 41.0,
        "homeGoals": 5.0,
        "possessionPercentage": 52.6,
        "oboxTarget": 6.0,
        "drops": 2.0,
        "tacklesLost": 37.0,
        "lastPlayerTackle": 2.0,
        "successfulPassesOppositionHalf": 973.0,
        "goalsConcededInsideBox": 8.0,
        "headedGoals": 1.0,
        "iboxBlocked": 12.0,
        "groundDuels": 335.0,
        "aerialDuelsWon": 90.0,
        "straightRedCards": 0.0,
        "cornersWon": 25.0,
        "successfulDribbles": 27.0,
        "blocks": 12.0,
        "gkUnsuccessfulDistribution": 6.0,
        "interceptions": 35.0,
        "penaltyGoals": 1.0,
        "unsuccessfulLaunches": 80.0,
        "foulAttemptedTackle": 28.0,
        "shotsOnConcededOutsideBox": 2.0,
        "goalConversion": 10.17,
        "expectedGoals": 10.1323,
        "yellowCards": 3.0
      }
    },
    {
      "teamMetadata": {
        "name": "Everton",
        "season": "2025",
        "id": "11",
        "shortName": "Everton",
        "abbr": "EVE"
      },
      "stats": {
        "duelsLost": 247.0,
        "penaltiesSaved": 1.0,
        "blockedShots": 20.0,
        "shotsOnTargetIncGoals": 12.0,
        "expectedGoalsOnTarget": 4.7543,
        "gamesPlayed": 5.0,
        "crossingAccuracy": 29.49,
        "totalPasses": 1832.0,
        "goals": 6.0,
        "offsides": 6.0,
        "awayGoals": 4.0,
        "tackleSuccess": 68.18,
        "oboxBlocked": 9.0,
        "passingAccuracy": 77.24,
        "iboxTarget": 5.0,
        "aerialDuelsLost": 83.0,
        "groundDuelsWon": 193.0,
        "successfulCornersIntoBox": 6.0,
        "penaltyGoalsConceded": 1.0,
        "expectedGoalsOnTargetConceded": 5.0691,
        "keyPassesAttemptAssists": 41.0,
        "successfulLaunches": 28.0,
        "totalFoulsWon": 62.0,
        "recoveries": 229.0,
        "passingPercentOppHalf": 69.69,
        "shotsOnConcededInsideBox": 9.0,
        "rightFootGoals": 3.0,
        "leftFootGoals": 2.0,
        "unsuccessfulDribbles": 43.0,
        "unsuccessfulCrossesAndCorners": 55.0,
        "timesTackled": 89.0,
        "freekickTotal": 2.0,
        "openPlayPasses": 1703.0,
        "gkSuccessfulDistribution": 44.0,
        "shotsOffTargetIncWoodwork": 25.0,
        "totalLossesOfPossession": 674.0,
        "tacklesWon": 60.0,
        "attemptsFromSetPieces": 2.0,
        "totalShotsConceded": 64.0,
        "totalFoulsConceded": 52.0,
        "unsuccessfulCornersIntoBox": 10.0,
        "successfulLongPasses": 120.0,
        "throwInsToOwnPlayer": 81.0,
        "touchesInOppBox": 122.0,
        "hitWoodwork": 1.0,
        "successfulPassesOwnHalf": 677.0,
        "handballsConceded": 4.0,
        "unsuccessfulLongPasses": 179.0,
        "unsuccessfulPassesOwnHalf": 96.0,
        "successfulCrossesOpenPlay": 14.0,
        "expectedAssists": 4.7438,
        "totalRedCards": 0.0,
        "expectedGoalsFreekick": 0.0699,
        "catches": 4.0,
        "overruns": 2.0,
        "unsuccessfulPassesOppositionHalf": 376.0,
        "totalShots": 37.0,
        "unsuccessfulShortPasses": 238.0,
        "goalAssists": 6.0,
        "successfulLayoffs": 33.0,
        "unsuccessfulCrossesOpenPlay": 39.0,
        "goalKicks": 45.0,
        "cornersTakenInclShortCorners": 20.0,
        "aerialDuels": 192.0,
        "cleanSheets": 2.0,
        "shootingAccuracy": 32.43,
        "successfulCrossesAndCorners": 23.0,
        "unsuccessfulLayoffs": 4.0,
        "duelsWon": 302.0,
        "penaltiesConceded": 2.0,
        "putthroughBlockedDistribution": 73.0,
        "successfulShortPasses": 1295.0,
        "throwInsToOppositionPlayer": 25.0,
        "successfulOpenPlayPasses": 1328.0,
        "totalClearances": 134.0,
        "goalsConceded": 5.0,
        "groundDuelsLost": 164.0,
        "duels": 549.0,
        "putthroughBlockedDistributionWon": 34.0,
        "homeGoals": 2.0,
        "possessionPercentage": 44.2,
        "oboxTarget": 1.0,
        "tacklesLost": 28.0,
        "lastPlayerTackle": 1.0,
        "successfulPassesOppositionHalf": 761.0,
        "goalsConcededInsideBox": 5.0,
        "headedGoals": 1.0,
        "iboxBlocked": 11.0,
        "groundDuels": 357.0,
        "aerialDuelsWon": 109.0,
        "straightRedCards": 0.0,
        "cornersWon": 20.0,
        "successfulDribbles": 43.0,
        "blocks": 28.0,
        "gkUnsuccessfulDistribution": 17.0,
        "interceptions": 41.0,
        "unsuccessfulLaunches": 105.0,
        "foulAttemptedTackle": 24.0,
        "shotsOnConcededOutsideBox": 6.0,
        "goalConversion": 16.22,
        "expectedGoals": 7.1126,
        "yellowCards": 13.0
      }
    },
    {
      "teamMetadata": {
        "name": "Liverpool",
        "season": "2025",
        "id": "14",
        "shortName": "Liverpool",
        "abbr": "LIV"
      },
      "stats": {
        "duelsLost": 232.0,
        "blockedShots": 24.0,
        "shotsOnTargetIncGoals": 24.0,
        "expectedGoalsOnTarget": 7.9351,
        "gamesPlayed": 5.0,
        "setPiecesGoals": 1.0,
        "crossingAccuracy": 22.47,
        "totalPasses": 2541.0,
        "goals": 11.0,
        "offsides": 5.0,
        "awayGoals": 4.0,
        "tackleSuccess": 64.71,
        "oboxBlocked": 14.0,
        "passingAccuracy": 84.73,
        "iboxTarget": 10.0,
        "aerialDuelsLost": 74.0,
        "goalsConcededOutsideBox": 1.0,
        "groundDuelsWon": 162.0,
        "successfulCornersIntoBox": 6.0,
        "expectedGoalsOnTargetConceded": 3.8064,
        "keyPassesAttemptAssists": 48.0,
        "successfulLaunches": 14.0,
        "totalFoulsWon": 54.0,
        "recoveries": 216.0,
        "passingPercentOppHalf": 79.37,
        "shotsOnConcededInsideBox": 8.0,
        "rightFootGoals": 10.0,
        "leftFootGoals": 1.0,
        "unsuccessfulDribbles": 34.0,
        "unsuccessfulCrossesAndCorners": 69.0,
        "timesTackled": 80.0,
        "freekickTotal": 3.0,
        "openPlayPasses": 2430.0,
        "gkSuccessfulDistribution": 41.0,
        "shotsOffTargetIncWoodwork": 23.0,
        "totalLossesOfPossession": 641.0,
        "tacklesWon": 44.0,
        "attemptsFromSetPieces": 3.0,
        "totalShotsConceded": 43.0,
        "totalFoulsConceded": 49.0,
        "unsuccessfulCornersIntoBox": 16.0,
        "successfulLongPasses": 100.0,
        "throwInsToOwnPlayer": 92.0,
        "touchesInOppBox": 151.0,
        "successfulPassesOwnHalf": 1053.0,
        "handballsConceded": 2.0,
        "unsuccessfulLongPasses": 131.0,
        "unsuccessfulPassesOwnHalf": 102.0,
        "successfulCrossesOpenPlay": 13.0,
        "expectedAssists": 4.351,
        "totalRedCards": 0.0,
        "expectedGoalsFreekick": 0.1271,
        "catches": 2.0,
        "overruns": 6.0,
        "unsuccessfulPassesOppositionHalf": 355.0,
        "totalShots": 47.0,
        "unsuccessfulShortPasses": 257.0,
        "goalAssists": 8.0,
        "successfulLayoffs": 48.0,
        "foulWonPenalty": 1.0,
        "unsuccessfulCrossesOpenPlay": 53.0,
        "goalKicks": 29.0,
        "cornersTakenInclShortCorners": 28.0,
        "aerialDuels": 178.0,
        "cleanSheets": 2.0,
        "shootingAccuracy": 51.06,
        "successfulCrossesAndCorners": 20.0,
        "unsuccessfulLayoffs": 4.0,
        "duelsWon": 266.0,
        "putthroughBlockedDistribution": 78.0,
        "successfulShortPasses": 2053.0,
        "throwInsToOppositionPlayer": 17.0,
        "successfulOpenPlayPasses": 2060.0,
        "totalClearances": 162.0,
        "goalsConceded": 5.0,
        "groundDuelsLost": 158.0,
        "duels": 498.0,
        "putthroughBlockedDistributionWon": 42.0,
        "homeGoals": 7.0,
        "possessionPercentage": 62.8,
        "oboxTarget": 3.0,
        "tacklesLost": 24.0,
        "lastPlayerTackle": 1.0,
        "successfulPassesOppositionHalf": 1120.0,
        "goalsConcededInsideBox": 4.0,
        "iboxBlocked": 10.0,
        "groundDuels": 320.0,
        "aerialDuelsWon": 104.0,
        "straightRedCards": 0.0,
        "cornersWon": 28.0,
        "successfulDribbles": 42.0,
        "blocks": 16.0,
        "gkUnsuccessfulDistribution": 7.0,
        "interceptions": 32.0,
        "penaltyGoals": 1.0,
        "unsuccessfulLaunches": 65.0,
        "foulAttemptedTackle": 20.0,
        "shotsOnConcededOutsideBox": 1.0,
        "goalConversion": 23.4,
        "expectedGoals": 6.979,
        "yellowCards": 10.0
      }
    },
    {
      "teamMetadata": {
        "name": "Nottingham Forest",
        "season": "2025",
        "id": "17",
        "shortName": "Nott'm Forest",
        "abbr": "NFO"
      },
      "stats": {
        "duelsLost": 233.0,
        "blockedShots": 18.0,
        "shotsOnTargetIncGoals": 18.0,
        "expectedGoalsOnTarget": 4.5096,
        "gamesPlayed": 5.0,
        "crossingAccuracy": 14.84,
        "totalPasses": 2509.0,
        "goals": 5.0,
        "offsides": 6.0,
        "awayGoals": 2.0,
        "tackleSuccess": 63.64,
        "oboxBlocked": 10.0,
        "passingAccuracy": 86.45,
        "iboxTarget": 9.0,
        "aerialDuelsLost": 65.0,
        "goalsConcededOutsideBox": 2.0,
        "groundDuelsWon": 140.0,
        "successfulCornersIntoBox": 3.0,
        "penaltyGoalsConceded": 2.0,
        "expectedGoalsOnTargetConceded": 8.9095,
        "keyPassesAttemptAssists": 38.0,
        "successfulLaunches": 25.0,
        "totalFoulsWon": 50.0,
        "recoveries": 229.0,
        "pointsGainedFromLosingPositions": 1.0,
        "passingPercentOppHalf": 81.83,
        "shotsOnConcededInsideBox": 18.0,
        "rightFootGoals": 3.0,
        "leftFootGoals": 1.0,
        "unsuccessfulDribbles": 40.0,
        "unsuccessfulCrossesAndCorners": 109.0,
        "timesTackled": 80.0,
        "openPlayPasses": 2401.0,
        "gkSuccessfulDistribution": 51.0,
        "shotsOffTargetIncWoodwork": 17.0,
        "totalLossesOfPossession": 630.0,
        "tacklesWon": 42.0,
        "totalShotsConceded": 58.0,
        "totalFoulsConceded": 54.0,
        "unsuccessfulCornersIntoBox": 18.0,
        "successfulLongPasses": 97.0,
        "throwInsToOwnPlayer": 75.0,
        "touchesInOppBox": 117.0,
        "hitWoodwork": 2.0,
        "successfulPassesOwnHalf": 980.0,
        "pointsDroppedFromWinningPositions": 2.0,
        "handballsConceded": 4.0,
        "unsuccessfulLongPasses": 122.0,
        "unsuccessfulPassesOwnHalf": 76.0,
        "successfulCrossesOpenPlay": 16.0,
        "expectedAssists": 3.5747,
        "totalRedCards": 0.0,
        "catches": 4.0,
        "overruns": 4.0,
        "unsuccessfulPassesOppositionHalf": 373.0,
        "totalShots": 35.0,
        "unsuccessfulShortPasses": 218.0,
        "goalAssists": 3.0,
        "successfulLayoffs": 56.0,
        "unsuccessfulCrossesOpenPlay": 87.0,
        "goalKicks": 38.0,
        "cornersTakenInclShortCorners": 26.0,
        "aerialDuels": 134.0,
        "shootingAccuracy": 51.43,
        "successfulCrossesAndCorners": 19.0,
        "unsuccessfulLayoffs": 1.0,
        "duelsWon": 209.0,
        "penaltiesConceded": 2.0,
        "putthroughBlockedDistribution": 86.0,
        "successfulShortPasses": 2072.0,
        "throwInsToOppositionPlayer": 20.0,
        "successfulOpenPlayPasses": 2072.0,
        "totalClearances": 103.0,
        "goalsConceded": 9.0,
        "groundDuelsLost": 168.0,
        "duels": 442.0,
        "putthroughBlockedDistributionWon": 40.0,
        "homeGoals": 3.0,
        "possessionPercentage": 56.1,
        "oboxTarget": 4.0,
        "tacklesLost": 24.0,
        "lastPlayerTackle": 1.0,
        "successfulPassesOppositionHalf": 1208.0,
        "goalsConcededInsideBox": 7.0,
        "headedGoals": 1.0,
        "iboxBlocked": 8.0,
        "groundDuels": 308.0,
        "aerialDuelsWon": 69.0,
        "straightRedCards": 0.0,
        "cornersWon": 26.0,
        "successfulDribbles": 30.0,
        "blocks": 11.0,
        "gkUnsuccessfulDistribution": 6.0,
        "interceptions": 43.0,
        "unsuccessfulLaunches": 53.0,
        "foulAttemptedTackle": 26.0,
        "shotsOnConcededOutsideBox": 7.0,
        "goalConversion": 14.29,
        "expectedGoals": 4.789,
        "yellowCards": 6.0
      }
    },
    {
      "teamMetadata": {
        "name": "Leeds United",
        "season": "2025",
        "id": "2",
        "shortName": "Leeds",
        "abbr": "LEE"
      },
      "stats": {
        "duelsLost": 265.0,
        "blockedShots": 20.0,
        "shotsOnTargetIncGoals": 12.0,
        "expectedGoalsOnTarget": 3.3689,
        "gamesPlayed": 5.0,
        "setPiecesGoals": 1.0,
        "crossingAccuracy": 19.12,
        "totalPasses": 1989.0,
        "goals": 4.0,
        "offsides": 7.0,
        "awayGoals": 3.0,
        "tackleSuccess": 64.04,
        "oboxBlocked": 8.0,
        "passingAccuracy": 81.05,
        "iboxTarget": 5.0,
        "aerialDuelsLost": 87.0,
        "groundDuelsWon": 175.0,
        "successfulCornersIntoBox": 6.0,
        "penaltyGoalsConceded": 1.0,
        "expectedGoalsOnTargetConceded": 5.2052,
        "keyPassesAttemptAssists": 29.0,
        "successfulLaunches": 17.0,
        "totalFoulsWon": 61.0,
        "recoveries": 232.0,
        "pointsGainedFromLosingPositions": 3.0,
        "passingPercentOppHalf": 71.31,
        "shotsOnConcededInsideBox": 14.0,
        "rightFootGoals": 2.0,
        "leftFootGoals": 1.0,
        "unsuccessfulDribbles": 46.0,
        "unsuccessfulCrossesAndCorners": 55.0,
        "timesTackled": 90.0,
        "freekickTotal": 2.0,
        "openPlayPasses": 1869.0,
        "gkSuccessfulDistribution": 44.0,
        "shotsOffTargetIncWoodwork": 18.0,
        "totalLossesOfPossession": 620.0,
        "tacklesWon": 57.0,
        "attemptsFromSetPieces": 2.0,
        "totalShotsConceded": 54.0,
        "totalFoulsConceded": 51.0,
        "unsuccessfulCornersIntoBox": 10.0,
        "successfulLongPasses": 93.0,
        "throwInsToOwnPlayer": 66.0,
        "touchesInOppBox": 87.0,
        "hitWoodwork": 1.0,
        "successfulPassesOwnHalf": 946.0,
        "ownGoalsConceded": 1.0,
        "unsuccessfulLongPasses": 154.0,
        "unsuccessfulPassesOwnHalf": 109.0,
        "successfulCrossesOpenPlay": 7.0,
        "expectedAssists": 2.3803,
        "totalRedCards": 0.0,
        "expectedGoalsFreekick": 0.1142,
        "catches": 4.0,
        "overruns": 5.0,
        "unsuccessfulPassesOppositionHalf": 323.0,
        "totalShots": 30.0,
        "unsuccessfulShortPasses": 223.0,
        "goalAssists": 1.0,
        "successfulLayoffs": 59.0,
        "foulWonPenalty": 1.0,
        "unsuccessfulCrossesOpenPlay": 40.0,
        "goalKicks": 40.0,
        "cornersTakenInclShortCorners": 17.0,
        "aerialDuels": 155.0,
        "cleanSheets": 2.0,
        "shootingAccuracy": 40.0,
        "successfulCrossesAndCorners": 13.0,
        "unsuccessfulLayoffs": 5.0,
        "duelsWon": 243.0,
        "penaltiesConceded": 1.0,
        "putthroughBlockedDistribution": 79.0,
        "successfulShortPasses": 1519.0,
        "throwInsToOppositionPlayer": 16.0,
        "successfulOpenPlayPasses": 1528.0,
        "totalClearances": 147.0,
        "goalsConceded": 7.0,
        "groundDuelsLost": 178.0,
        "duels": 508.0,
        "putthroughBlockedDistributionWon": 33.0,
        "homeGoals": 1.0,
        "possessionPercentage": 44.2,
        "oboxTarget": 3.0,
        "drops": 1.0,
        "tacklesLost": 32.0,
        "lastPlayerTackle": 1.0,
        "successfulPassesOppositionHalf": 679.0,
        "goalsConcededInsideBox": 7.0,
        "headedGoals": 1.0,
        "iboxBlocked": 12.0,
        "groundDuels": 353.0,
        "aerialDuelsWon": 68.0,
        "straightRedCards": 0.0,
        "cornersWon": 17.0,
        "successfulDribbles": 29.0,
        "blocks": 12.0,
        "gkUnsuccessfulDistribution": 22.0,
        "interceptions": 42.0,
        "penaltyGoals": 1.0,
        "unsuccessfulLaunches": 76.0,
        "foulAttemptedTackle": 22.0,
        "shotsOnConcededOutsideBox": 4.0,
        "goalConversion": 13.33,
        "expectedGoals": 4.2568,
        "yellowCards": 6.0
      }
    },
    {
      "teamMetadata": {
        "name": "West Ham United",
        "season": "2025",
        "id": "21",
        "shortName": "West Ham",
        "abbr": "WHU"
      },
      "stats": {
        "duelsLost": 248.0,
        "blockedShots": 10.0,
        "shotsOnTargetIncGoals": 23.0,
        "expectedGoalsOnTarget": 5.8214,
        "gamesPlayed": 5.0,
        "crossingAccuracy": 31.87,
        "totalPasses": 2087.0,
        "goals": 5.0,
        "offsides": 5.0,
        "awayGoals": 3.0,
        "tackleSuccess": 60.66,
        "oboxBlocked": 6.0,
        "passingAccuracy": 83.23,
        "iboxTarget": 16.0,
        "aerialDuelsLost": 87.0,
        "groundDuelsWon": 142.0,
        "successfulCornersIntoBox": 11.0,
        "expectedGoalsOnTargetConceded": 10.6682,
        "keyPassesAttemptAssists": 38.0,
        "successfulLaunches": 24.0,
        "totalFoulsWon": 41.0,
        "recoveries": 202.0,
        "passingPercentOppHalf": 74.43,
        "shotsOnConcededInsideBox": 23.0,
        "leftFootGoals": 3.0,
        "unsuccessfulDribbles": 45.0,
        "unsuccessfulCrossesAndCorners": 62.0,
        "timesTackled": 90.0,
        "freekickTotal": 1.0,
        "openPlayPasses": 1982.0,
        "gkSuccessfulDistribution": 52.0,
        "shotsOffTargetIncWoodwork": 18.0,
        "totalLossesOfPossession": 581.0,
        "tacklesWon": 37.0,
        "attemptsFromSetPieces": 1.0,
        "totalShotsConceded": 65.0,
        "totalFoulsConceded": 46.0,
        "unsuccessfulCornersIntoBox": 17.0,
        "successfulLongPasses": 92.0,
        "throwInsToOwnPlayer": 88.0,
        "touchesInOppBox": 95.0,
        "successfulPassesOwnHalf": 919.0,
        "pointsDroppedFromWinningPositions": 3.0,
        "unsuccessfulLongPasses": 150.0,
        "unsuccessfulPassesOwnHalf": 69.0,
        "successfulCrossesOpenPlay": 15.0,
        "expectedAssists": 3.4116,
        "totalRedCards": 1.0,
        "expectedGoalsFreekick": 0.1057,
        "catches": 6.0,
        "overruns": 5.0,
        "unsuccessfulPassesOppositionHalf": 343.0,
        "totalShots": 41.0,
        "unsuccessfulShortPasses": 200.0,
        "goalAssists": 4.0,
        "successfulLayoffs": 49.0,
        "foulWonPenalty": 1.0,
        "unsuccessfulCrossesOpenPlay": 40.0,
        "goalKicks": 42.0,
        "cornersTakenInclShortCorners": 31.0,
        "aerialDuels": 170.0,
        "cleanSheets": 1.0,
        "shootingAccuracy": 56.1,
        "successfulCrossesAndCorners": 29.0,
        "unsuccessfulLayoffs": 5.0,
        "duelsWon": 225.0,
        "putthroughBlockedDistribution": 81.0,
        "successfulShortPasses": 1645.0,
        "throwInsToOppositionPlayer": 7.0,
        "successfulOpenPlayPasses": 1660.0,
        "totalClearances": 140.0,
        "goalsConceded": 13.0,
        "groundDuelsLost": 161.0,
        "duels": 473.0,
        "putthroughBlockedDistributionWon": 32.0,
        "homeGoals": 2.0,
        "possessionPercentage": 47.4,
        "oboxTarget": 2.0,
        "tacklesLost": 24.0,
        "lastPlayerTackle": 1.0,
        "successfulPassesOppositionHalf": 847.0,
        "goalsConcededInsideBox": 13.0,
        "headedGoals": 2.0,
        "iboxBlocked": 4.0,
        "groundDuels": 303.0,
        "aerialDuelsWon": 83.0,
        "straightRedCards": 1.0,
        "cornersWon": 31.0,
        "successfulDribbles": 40.0,
        "blocks": 18.0,
        "gkUnsuccessfulDistribution": 15.0,
        "interceptions": 29.0,
        "penaltyGoals": 1.0,
        "unsuccessfulLaunches": 83.0,
        "foulAttemptedTackle": 21.0,
        "goalConversion": 12.2,
        "expectedGoals": 4.9719,
        "yellowCards": 4.0
      }
    },
    {
      "teamMetadata": {
        "name": "Arsenal",
        "season": "2025",
        "id": "3",
        "shortName": "Arsenal",
        "abbr": "ARS"
      },
      "stats": {
        "duelsLost": 225.0,
        "blockedShots": 22.0,
        "shotsOnTargetIncGoals": 17.0,
        "expectedGoalsOnTarget": 8.1301,
        "gamesPlayed": 5.0,
        "crossingAccuracy": 23.23,
        "totalPasses": 2324.0,
        "goals": 10.0,
        "offsides": 8.0,
        "awayGoals": 1.0,
        "tackleSuccess": 62.34,
        "oboxBlocked": 7.0,
        "passingAccuracy": 86.19,
        "iboxTarget": 6.0,
        "aerialDuelsLost": 63.0,
        "goalsConcededOutsideBox": 1.0,
        "groundDuelsWon": 165.0,
        "successfulCornersIntoBox": 9.0,
        "expectedGoalsOnTargetConceded": 2.3389,
        "keyPassesAttemptAssists": 36.0,
        "successfulLaunches": 32.0,
        "totalFoulsWon": 49.0,
        "recoveries": 227.0,
        "pointsGainedFromLosingPositions": 1.0,
        "passingPercentOppHalf": 77.39,
        "shotsOnConcededInsideBox": 12.0,
        "rightFootGoals": 7.0,
        "unsuccessfulDribbles": 48.0,
        "unsuccessfulCrossesAndCorners": 76.0,
        "timesTackled": 76.0,
        "freekickTotal": 2.0,
        "openPlayPasses": 2246.0,
        "gkSuccessfulDistribution": 39.0,
        "shotsOffTargetIncWoodwork": 27.0,
        "totalLossesOfPossession": 590.0,
        "tacklesWon": 48.0,
        "attemptsFromSetPieces": 2.0,
        "totalShotsConceded": 44.0,
        "totalFoulsConceded": 56.0,
        "unsuccessfulCornersIntoBox": 23.0,
        "successfulLongPasses": 117.0,
        "throwInsToOwnPlayer": 73.0,
        "touchesInOppBox": 160.0,
        "hitWoodwork": 1.0,
        "successfulPassesOwnHalf": 1113.0,
        "handballsConceded": 1.0,
        "unsuccessfulLongPasses": 100.0,
        "unsuccessfulPassesOwnHalf": 61.0,
        "successfulCrossesOpenPlay": 12.0,
        "expectedAssists": 4.5038,
        "totalRedCards": 0.0,
        "expectedGoalsFreekick": 0.0752,
        "catches": 3.0,
        "overruns": 7.0,
        "unsuccessfulPassesOppositionHalf": 336.0,
        "totalShots": 44.0,
        "unsuccessfulShortPasses": 221.0,
        "goalAssists": 7.0,
        "successfulLayoffs": 39.0,
        "foulWonPenalty": 1.0,
        "unsuccessfulCrossesOpenPlay": 49.0,
        "goalKicks": 23.0,
        "cornersTakenInclShortCorners": 33.0,
        "aerialDuels": 125.0,
        "cleanSheets": 3.0,
        "shootingAccuracy": 38.64,
        "successfulCrossesAndCorners": 23.0,
        "unsuccessfulLayoffs": 6.0,
        "duelsWon": 227.0,
        "putthroughBlockedDistribution": 81.0,
        "successfulShortPasses": 1886.0,
        "throwInsToOppositionPlayer": 18.0,
        "successfulOpenPlayPasses": 1944.0,
        "totalClearances": 89.0,
        "goalsConceded": 2.0,
        "groundDuelsLost": 162.0,
        "duels": 452.0,
        "putthroughBlockedDistributionWon": 42.0,
        "homeGoals": 9.0,
        "possessionPercentage": 55.1,
        "oboxTarget": 1.0,
        "drops": 2.0,
        "tacklesLost": 29.0,
        "lastPlayerTackle": 1.0,
        "successfulPassesOppositionHalf": 913.0,
        "goalsConcededInsideBox": 1.0,
        "headedGoals": 3.0,
        "iboxBlocked": 15.0,
        "groundDuels": 327.0,
        "aerialDuelsWon": 62.0,
        "straightRedCards": 0.0,
        "cornersWon": 33.0,
        "successfulDribbles": 41.0,
        "blocks": 17.0,
        "gkUnsuccessfulDistribution": 7.0,
        "interceptions": 30.0,
        "penaltyGoals": 1.0,
        "unsuccessfulLaunches": 54.0,
        "foulAttemptedTackle": 30.0,
        "shotsOnConcededOutsideBox": 3.0,
        "goalConversion": 22.73,
        "expectedGoals": 7.3949,
        "yellowCards": 8.0
      }
    },
    {
      "teamMetadata": {
        "name": "Crystal Palace",
        "season": "2025",
        "id": "31",
        "shortName": "Crystal Palace",
        "abbr": "CRY"
      },
      "stats": {
        "duelsLost": 233.0,
        "blockedShots": 15.0,
        "shotsOnTargetIncGoals": 21.0,
        "expectedGoalsOnTarget": 6.2676,
        "gamesPlayed": 5.0,
        "crossingAccuracy": 26.92,
        "totalPasses": 1825.0,
        "goals": 6.0,
        "offsides": 6.0,
        "awayGoals": 5.0,
        "tackleSuccess": 65.96,
        "oboxBlocked": 8.0,
        "passingAccuracy": 80.93,
        "iboxTarget": 9.0,
        "aerialDuelsLost": 79.0,
        "groundDuelsWon": 163.0,
        "successfulCornersIntoBox": 5.0,
        "expectedGoalsOnTargetConceded": 3.4819,
        "keyPassesAttemptAssists": 35.0,
        "successfulLaunches": 26.0,
        "totalFoulsWon": 50.0,
        "recoveries": 206.0,
        "passingPercentOppHalf": 71.73,
        "shotsOnConcededInsideBox": 10.0,
        "rightFootGoals": 4.0,
        "unsuccessfulDribbles": 17.0,
        "unsuccessfulCrossesAndCorners": 57.0,
        "timesTackled": 58.0,
        "openPlayPasses": 1715.0,
        "gkSuccessfulDistribution": 56.0,
        "shotsOffTargetIncWoodwork": 21.0,
        "totalLossesOfPossession": 553.0,
        "tacklesWon": 62.0,
        "totalShotsConceded": 55.0,
        "totalFoulsConceded": 52.0,
        "unsuccessfulCornersIntoBox": 10.0,
        "successfulLongPasses": 92.0,
        "clearancesOffTheLine": 1.0,
        "throwInsToOwnPlayer": 60.0,
        "touchesInOppBox": 91.0,
        "hitWoodwork": 3.0,
        "successfulPassesOwnHalf": 840.0,
        "pointsDroppedFromWinningPositions": 2.0,
        "handballsConceded": 3.0,
        "unsuccessfulLongPasses": 145.0,
        "unsuccessfulPassesOwnHalf": 97.0,
        "successfulCrossesOpenPlay": 15.0,
        "expectedAssists": 4.5123,
        "totalRedCards": 0.0,
        "catches": 5.0,
        "unsuccessfulPassesOppositionHalf": 308.0,
        "totalShots": 42.0,
        "unsuccessfulShortPasses": 203.0,
        "goalAssists": 2.0,
        "successfulLayoffs": 29.0,
        "foulWonPenalty": 1.0,
        "unsuccessfulCrossesOpenPlay": 40.0,
        "goalKicks": 53.0,
        "cornersTakenInclShortCorners": 17.0,
        "aerialDuels": 163.0,
        "cleanSheets": 3.0,
        "shootingAccuracy": 50.0,
        "successfulCrossesAndCorners": 21.0,
        "duelsWon": 247.0,
        "putthroughBlockedDistribution": 74.0,
        "successfulShortPasses": 1385.0,
        "throwInsToOppositionPlayer": 16.0,
        "successfulOpenPlayPasses": 1393.0,
        "totalClearances": 159.0,
        "goalsConceded": 2.0,
        "groundDuelsLost": 154.0,
        "duels": 480.0,
        "putthroughBlockedDistributionWon": 39.0,
        "homeGoals": 1.0,
        "possessionPercentage": 42.9,
        "oboxTarget": 6.0,
        "tacklesLost": 32.0,
        "lastPlayerTackle": 2.0,
        "successfulPassesOppositionHalf": 658.0,
        "goalsConcededInsideBox": 2.0,
        "headedGoals": 2.0,
        "iboxBlocked": 7.0,
        "groundDuels": 317.0,
        "aerialDuelsWon": 84.0,
        "straightRedCards": 0.0,
        "cornersWon": 17.0,
        "successfulDribbles": 21.0,
        "blocks": 15.0,
        "gkUnsuccessfulDistribution": 16.0,
        "interceptions": 40.0,
        "penaltyGoals": 1.0,
        "unsuccessfulLaunches": 64.0,
        "foulAttemptedTackle": 24.0,
        "shotsOnConcededOutsideBox": 1.0,
        "goalConversion": 14.29,
        "expectedGoals": 8.489,
        "yellowCards": 13.0
      }
    },
    {
      "teamMetadata": {
        "name": "Brighton and Hove Albion",
        "season": "2025",
        "id": "36",
        "shortName": "Brighton",
        "abbr": "BHA"
      },
      "stats": {
        "duelsLost": 284.0,
        "blockedShots": 11.0,
        "shotsOnTargetIncGoals": 21.0,
        "expectedGoalsOnTarget": 8.1777,
        "gamesPlayed": 5.0,
        "crossingAccuracy": 27.27,
        "totalPasses": 1913.0,
        "goals": 6.0,
        "offsides": 10.0,
        "awayGoals": 1.0,
        "tackleSuccess": 64.29,
        "oboxBlocked": 4.0,
        "passingAccuracy": 80.97,
        "iboxTarget": 8.0,
        "aerialDuelsLost": 84.0,
        "goalsConcededOutsideBox": 2.0,
        "groundDuelsWon": 196.0,
        "successfulCornersIntoBox": 4.0,
        "penaltyGoalsConceded": 1.0,
        "expectedGoalsOnTargetConceded": 6.0804,
        "keyPassesAttemptAssists": 36.0,
        "successfulLaunches": 20.0,
        "totalFoulsWon": 63.0,
        "recoveries": 244.0,
        "pointsGainedFromLosingPositions": 3.0,
        "passingPercentOppHalf": 68.87,
        "shotsOnConcededInsideBox": 13.0,
        "rightFootGoals": 3.0,
        "leftFootGoals": 2.0,
        "unsuccessfulDribbles": 37.0,
        "unsuccessfulCrossesAndCorners": 40.0,
        "timesTackled": 89.0,
        "freekickTotal": 1.0,
        "openPlayPasses": 1788.0,
        "gkSuccessfulDistribution": 61.0,
        "shotsOffTargetIncWoodwork": 21.0,
        "totalLossesOfPossession": 613.0,
        "tacklesWon": 63.0,
        "attemptsFromSetPieces": 1.0,
        "totalShotsConceded": 54.0,
        "totalFoulsConceded": 67.0,
        "unsuccessfulCornersIntoBox": 10.0,
        "successfulLongPasses": 100.0,
        "throwInsToOwnPlayer": 66.0,
        "touchesInOppBox": 117.0,
        "hitWoodwork": 2.0,
        "successfulPassesOwnHalf": 945.0,
        "pointsDroppedFromWinningPositions": 4.0,
        "ownGoalsConceded": 1.0,
        "handballsConceded": 1.0,
        "unsuccessfulLongPasses": 152.0,
        "unsuccessfulPassesOwnHalf": 91.0,
        "successfulCrossesOpenPlay": 9.0,
        "expectedAssists": 2.8544,
        "totalRedCards": 0.0,
        "expectedGoalsFreekick": 0.0323,
        "catches": 2.0,
        "overruns": 6.0,
        "unsuccessfulPassesOppositionHalf": 313.0,
        "totalShots": 42.0,
        "unsuccessfulShortPasses": 212.0,
        "goalAssists": 3.0,
        "successfulLayoffs": 32.0,
        "foulWonPenalty": 3.0,
        "unsuccessfulCrossesOpenPlay": 28.0,
        "goalKicks": 48.0,
        "cornersTakenInclShortCorners": 15.0,
        "aerialDuels": 145.0,
        "shootingAccuracy": 50.0,
        "successfulCrossesAndCorners": 15.0,
        "unsuccessfulLayoffs": 8.0,
        "duelsWon": 257.0,
        "penaltiesConceded": 1.0,
        "putthroughBlockedDistribution": 85.0,
        "successfulShortPasses": 1449.0,
        "throwInsToOppositionPlayer": 14.0,
        "successfulOpenPlayPasses": 1448.0,
        "totalClearances": 136.0,
        "goalsConceded": 8.0,
        "groundDuelsLost": 200.0,
        "duels": 541.0,
        "putthroughBlockedDistributionWon": 49.0,
        "homeGoals": 5.0,
        "possessionPercentage": 45.8,
        "oboxTarget": 7.0,
        "tacklesLost": 35.0,
        "lastPlayerTackle": 3.0,
        "successfulPassesOppositionHalf": 619.0,
        "goalsConcededInsideBox": 6.0,
        "headedGoals": 1.0,
        "iboxBlocked": 7.0,
        "groundDuels": 396.0,
        "aerialDuelsWon": 61.0,
        "straightRedCards": 0.0,
        "cornersWon": 15.0,
        "successfulDribbles": 36.0,
        "blocks": 9.0,
        "gkUnsuccessfulDistribution": 10.0,
        "interceptions": 33.0,
        "penaltyGoals": 2.0,
        "unsuccessfulLaunches": 78.0,
        "foulAttemptedTackle": 36.0,
        "shotsOnConcededOutsideBox": 4.0,
        "goalConversion": 14.29,
        "expectedGoals": 8.1498,
        "yellowCards": 13.0
      }
    },
    {
      "teamMetadata": {
        "name": "Wolverhampton Wanderers",
        "season": "2025",
        "id": "39",
        "shortName": "Wolves",
        "abbr": "WOL"
      },
      "stats": {
        "duelsLost": 273.0,
        "blockedShots": 16.0,
        "shotsOnTargetIncGoals": 17.0,
        "expectedGoalsOnTarget": 3.8013,
        "gamesPlayed": 5.0,
        "crossingAccuracy": 33.01,
        "totalPasses": 2075.0,
        "goals": 3.0,
        "offsides": 8.0,
        "awayGoals": 0.0,
        "tackleSuccess": 58.41,
        "oboxBlocked": 9.0,
        "passingAccuracy": 79.81,
        "iboxTarget": 11.0,
        "aerialDuelsLost": 82.0,
        "goalsConcededOutsideBox": 2.0,
        "groundDuelsWon": 190.0,
        "successfulCornersIntoBox": 2.0,
        "expectedGoalsOnTargetConceded": 9.0719,
        "keyPassesAttemptAssists": 36.0,
        "successfulLaunches": 22.0,
        "totalFoulsWon": 47.0,
        "recoveries": 241.0,
        "passingPercentOppHalf": 71.74,
        "shotsOnConcededInsideBox": 15.0,
        "rightFootGoals": 1.0,
        "leftFootGoals": 2.0,
        "unsuccessfulDribbles": 30.0,
        "unsuccessfulCrossesAndCorners": 69.0,
        "timesTackled": 76.0,
        "freekickTotal": 2.0,
        "openPlayPasses": 1966.0,
        "gkSuccessfulDistribution": 40.0,
        "shotsOffTargetIncWoodwork": 18.0,
        "totalLossesOfPossession": 673.0,
        "tacklesWon": 66.0,
        "attemptsFromSetPieces": 2.0,
        "totalShotsConceded": 61.0,
        "totalFoulsConceded": 72.0,
        "unsuccessfulCornersIntoBox": 14.0,
        "successfulLongPasses": 121.0,
        "throwInsToOwnPlayer": 103.0,
        "touchesInOppBox": 116.0,
        "successfulPassesOwnHalf": 864.0,
        "pointsDroppedFromWinningPositions": 3.0,
        "unsuccessfulLongPasses": 159.0,
        "unsuccessfulPassesOwnHalf": 107.0,
        "successfulCrossesOpenPlay": 31.0,
        "expectedAssists": 3.0992,
        "totalRedCards": 1.0,
        "expectedGoalsFreekick": 0.1485,
        "catches": 4.0,
        "overruns": 6.0,
        "unsuccessfulPassesOppositionHalf": 381.0,
        "totalShots": 35.0,
        "unsuccessfulShortPasses": 260.0,
        "goalAssists": 3.0,
        "successfulLayoffs": 36.0,
        "unsuccessfulCrossesOpenPlay": 52.0,
        "goalKicks": 32.0,
        "cornersTakenInclShortCorners": 17.0,
        "aerialDuels": 166.0,
        "shootingAccuracy": 48.57,
        "successfulCrossesAndCorners": 34.0,
        "unsuccessfulLayoffs": 4.0,
        "duelsWon": 274.0,
        "putthroughBlockedDistribution": 74.0,
        "successfulShortPasses": 1535.0,
        "throwInsToOppositionPlayer": 15.0,
        "successfulOpenPlayPasses": 1574.0,
        "totalClearances": 119.0,
        "goalsConceded": 12.0,
        "groundDuelsLost": 191.0,
        "duels": 547.0,
        "putthroughBlockedDistributionWon": 32.0,
        "homeGoals": 3.0,
        "possessionPercentage": 48.3,
        "oboxTarget": 3.0,
        "tacklesLost": 47.0,
        "lastPlayerTackle": 3.0,
        "successfulPassesOppositionHalf": 826.0,
        "goalsConcededInsideBox": 10.0,
        "iboxBlocked": 7.0,
        "groundDuels": 381.0,
        "aerialDuelsWon": 84.0,
        "straightRedCards": 1.0,
        "cornersWon": 17.0,
        "successfulDribbles": 30.0,
        "blocks": 18.0,
        "gkUnsuccessfulDistribution": 14.0,
        "interceptions": 42.0,
        "unsuccessfulLaunches": 72.0,
        "foulAttemptedTackle": 39.0,
        "shotsOnConcededOutsideBox": 5.0,
        "goalConversion": 8.57,
        "expectedGoals": 4.4171,
        "yellowCards": 10.0
      }
    },
    {
      "teamMetadata": {
        "name": "Newcastle United",
        "season": "2025",
        "id": "4",
        "shortName": "Newcastle",
        "abbr": "NEW"
      },
      "stats": {
        "duelsLost": 231.0,
        "blockedShots": 19.0,
        "shotsOnTargetIncGoals": 13.0,
        "expectedGoalsOnTarget": 4.4943,
        "gamesPlayed": 5.0,
        "crossingAccuracy": 21.05,
        "totalPasses": 2084.0,
        "goals": 3.0,
        "offsides": 4.0,
        "awayGoals": 0.0,
        "tackleSuccess": 54.1,
        "oboxBlocked": 8.0,
        "passingAccuracy": 80.04,
        "iboxTarget": 7.0,
        "aerialDuelsLost": 68.0,
        "goalsConcededOutsideBox": 1.0,
        "groundDuelsWon": 152.0,
        "successfulCornersIntoBox": 8.0,
        "expectedGoalsOnTargetConceded": 3.1769,
        "keyPassesAttemptAssists": 41.0,
        "successfulLaunches": 14.0,
        "totalFoulsWon": 62.0,
        "recoveries": 256.0,
        "passingPercentOppHalf": 73.21,
        "shotsOnConcededInsideBox": 11.0,
        "leftFootGoals": 1.0,
        "unsuccessfulDribbles": 41.0,
        "unsuccessfulCrossesAndCorners": 90.0,
        "timesTackled": 73.0,
        "freekickTotal": 1.0,
        "openPlayPasses": 1978.0,
        "gkSuccessfulDistribution": 51.0,
        "shotsOffTargetIncWoodwork": 22.0,
        "totalLossesOfPossession": 693.0,
        "tacklesWon": 33.0,
        "attemptsFromSetPieces": 1.0,
        "totalShotsConceded": 37.0,
        "totalFoulsConceded": 63.0,
        "unsuccessfulCornersIntoBox": 20.0,
        "successfulLongPasses": 105.0,
        "throwInsToOwnPlayer": 86.0,
        "touchesInOppBox": 118.0,
        "hitWoodwork": 1.0,
        "successfulPassesOwnHalf": 799.0,
        "handballsConceded": 3.0,
        "unsuccessfulLongPasses": 161.0,
        "unsuccessfulPassesOwnHalf": 98.0,
        "successfulCrossesOpenPlay": 15.0,
        "expectedAssists": 3.4812,
        "totalRedCards": 1.0,
        "expectedGoalsFreekick": 0.0423,
        "catches": 9.0,
        "overruns": 7.0,
        "unsuccessfulPassesOppositionHalf": 408.0,
        "totalShots": 35.0,
        "unsuccessfulShortPasses": 255.0,
        "goalAssists": 2.0,
        "successfulLayoffs": 30.0,
        "unsuccessfulCrossesOpenPlay": 69.0,
        "goalKicks": 31.0,
        "cornersTakenInclShortCorners": 30.0,
        "aerialDuels": 154.0,
        "cleanSheets": 4.0,
        "shootingAccuracy": 37.14,
        "successfulCrossesAndCorners": 24.0,
        "unsuccessfulLayoffs": 4.0,
        "duelsWon": 238.0,
        "putthroughBlockedDistribution": 84.0,
        "successfulShortPasses": 1563.0,
        "throwInsToOppositionPlayer": 25.0,
        "successfulOpenPlayPasses": 1607.0,
        "totalClearances": 104.0,
        "goalsConceded": 3.0,
        "groundDuelsLost": 163.0,
        "duels": 469.0,
        "putthroughBlockedDistributionWon": 34.0,
        "homeGoals": 3.0,
        "possessionPercentage": 51.3,
        "oboxTarget": 3.0,
        "drops": 2.0,
        "tacklesLost": 28.0,
        "successfulPassesOppositionHalf": 893.0,
        "goalsConcededInsideBox": 2.0,
        "headedGoals": 2.0,
        "iboxBlocked": 11.0,
        "groundDuels": 315.0,
        "aerialDuelsWon": 86.0,
        "straightRedCards": 1.0,
        "cornersWon": 30.0,
        "successfulDribbles": 32.0,
        "blocks": 11.0,
        "gkUnsuccessfulDistribution": 16.0,
        "interceptions": 42.0,
        "unsuccessfulLaunches": 82.0,
        "foulAttemptedTackle": 27.0,
        "shotsOnConcededOutsideBox": 2.0,
        "goalConversion": 8.57,
        "expectedGoals": 4.5681,
        "yellowCards": 6.0
      }
    },
    {
      "teamMetadata": {
        "name": "Manchester City",
        "season": "2025",
        "id": "43",
        "shortName": "Man City",
        "abbr": "MCI"
      },
      "stats": {
        "duelsLost": 235.0,
        "blockedShots": 8.0,
        "shotsOnTargetIncGoals": 20.0,
        "expectedGoalsOnTarget": 7.4083,
        "gamesPlayed": 5.0,
        "crossingAccuracy": 26.0,
        "totalPasses": 2383.0,
        "goals": 9.0,
        "offsides": 4.0,
        "awayGoals": 6.0,
        "tackleSuccess": 55.7,
        "oboxBlocked": 6.0,
        "passingAccuracy": 85.61,
        "iboxTarget": 9.0,
        "aerialDuelsLost": 48.0,
        "groundDuelsWon": 189.0,
        "successfulCornersIntoBox": 5.0,
        "penaltyGoalsConceded": 1.0,
        "expectedGoalsOnTargetConceded": 7.27,
        "keyPassesAttemptAssists": 32.0,
        "successfulLaunches": 19.0,
        "totalFoulsWon": 58.0,
        "recoveries": 235.0,
        "passingPercentOppHalf": 80.61,
        "shotsOnConcededInsideBox": 17.0,
        "rightFootGoals": 2.0,
        "leftFootGoals": 6.0,
        "unsuccessfulDribbles": 51.0,
        "unsuccessfulCrossesAndCorners": 37.0,
        "timesTackled": 109.0,
        "freekickTotal": 1.0,
        "openPlayPasses": 2263.0,
        "gkSuccessfulDistribution": 39.0,
        "shotsOffTargetIncWoodwork": 27.0,
        "totalLossesOfPossession": 602.0,
        "tacklesWon": 44.0,
        "attemptsFromSetPieces": 1.0,
        "totalShotsConceded": 57.0,
        "totalFoulsConceded": 46.0,
        "unsuccessfulCornersIntoBox": 10.0,
        "successfulLongPasses": 88.0,
        "throwInsToOwnPlayer": 89.0,
        "touchesInOppBox": 119.0,
        "hitWoodwork": 1.0,
        "successfulPassesOwnHalf": 1059.0,
        "pointsDroppedFromWinningPositions": 5.0,
        "handballsConceded": 1.0,
        "unsuccessfulLongPasses": 125.0,
        "unsuccessfulPassesOwnHalf": 107.0,
        "successfulCrossesOpenPlay": 8.0,
        "expectedAssists": 6.3923,
        "totalRedCards": 0.0,
        "expectedGoalsFreekick": 0.1217,
        "catches": 2.0,
        "overruns": 12.0,
        "unsuccessfulPassesOppositionHalf": 273.0,
        "totalShots": 47.0,
        "unsuccessfulShortPasses": 218.0,
        "goalAssists": 8.0,
        "successfulLayoffs": 55.0,
        "unsuccessfulCrossesOpenPlay": 22.0,
        "goalKicks": 36.0,
        "cornersTakenInclShortCorners": 19.0,
        "aerialDuels": 119.0,
        "cleanSheets": 2.0,
        "shootingAccuracy": 42.55,
        "successfulCrossesAndCorners": 13.0,
        "unsuccessfulLayoffs": 5.0,
        "duelsWon": 260.0,
        "penaltiesConceded": 1.0,
        "putthroughBlockedDistribution": 82.0,
        "successfulShortPasses": 1952.0,
        "throwInsToOppositionPlayer": 17.0,
        "successfulOpenPlayPasses": 1950.0,
        "totalClearances": 153.0,
        "goalsConceded": 5.0,
        "groundDuelsLost": 187.0,
        "duels": 495.0,
        "putthroughBlockedDistributionWon": 33.0,
        "homeGoals": 3.0,
        "possessionPercentage": 52.3,
        "oboxTarget": 2.0,
        "tacklesLost": 35.0,
        "successfulPassesOppositionHalf": 994.0,
        "goalsConcededInsideBox": 5.0,
        "headedGoals": 1.0,
        "iboxBlocked": 2.0,
        "groundDuels": 376.0,
        "aerialDuelsWon": 71.0,
        "straightRedCards": 0.0,
        "cornersWon": 19.0,
        "successfulDribbles": 52.0,
        "blocks": 11.0,
        "gkUnsuccessfulDistribution": 13.0,
        "interceptions": 37.0,
        "unsuccessfulLaunches": 70.0,
        "foulAttemptedTackle": 18.0,
        "shotsOnConcededOutsideBox": 3.0,
        "goalConversion": 19.15,
        "expectedGoals": 9.338,
        "yellowCards": 7.0
      }
    },
    {
      "teamMetadata": {
        "name": "Fulham",
        "season": "2025",
        "id": "54",
        "shortName": "Fulham",
        "abbr": "FUL"
      },
      "stats": {
        "duelsLost": 260.0,
        "blockedShots": 14.0,
        "shotsOnTargetIncGoals": 15.0,
        "expectedGoalsOnTarget": 3.9382,
        "gamesPlayed": 5.0,
        "crossingAccuracy": 26.8,
        "totalPasses": 2164.0,
        "goals": 6.0,
        "offsides": 8.0,
        "awayGoals": 1.0,
        "tackleSuccess": 54.64,
        "oboxBlocked": 7.0,
        "passingAccuracy": 83.32,
        "iboxTarget": 7.0,
        "aerialDuelsLost": 84.0,
        "ownGoalsAccrued": 2.0,
        "groundDuelsWon": 182.0,
        "successfulCornersIntoBox": 9.0,
        "penaltyGoalsConceded": 2.0,
        "expectedGoalsOnTargetConceded": 6.1526,
        "keyPassesAttemptAssists": 35.0,
        "successfulLaunches": 20.0,
        "totalFoulsWon": 64.0,
        "recoveries": 205.0,
        "pointsGainedFromLosingPositions": 5.0,
        "passingPercentOppHalf": 75.87,
        "shotsOnConcededInsideBox": 14.0,
        "rightFootGoals": 2.0,
        "leftFootGoals": 2.0,
        "unsuccessfulDribbles": 44.0,
        "unsuccessfulCrossesAndCorners": 71.0,
        "timesTackled": 86.0,
        "freekickTotal": 2.0,
        "openPlayPasses": 2047.0,
        "gkSuccessfulDistribution": 56.0,
        "shotsOffTargetIncWoodwork": 21.0,
        "totalLossesOfPossession": 630.0,
        "tacklesWon": 53.0,
        "attemptsFromSetPieces": 2.0,
        "totalShotsConceded": 51.0,
        "totalFoulsConceded": 75.0,
        "unsuccessfulCornersIntoBox": 11.0,
        "successfulLongPasses": 116.0,
        "throwInsToOwnPlayer": 88.0,
        "touchesInOppBox": 114.0,
        "successfulPassesOwnHalf": 979.0,
        "ownGoalsConceded": 1.0,
        "handballsConceded": 2.0,
        "unsuccessfulLongPasses": 130.0,
        "unsuccessfulPassesOwnHalf": 99.0,
        "successfulCrossesOpenPlay": 16.0,
        "expectedAssists": 4.2833,
        "totalRedCards": 0.0,
        "expectedGoalsFreekick": 0.1604,
        "catches": 4.0,
        "overruns": 5.0,
        "unsuccessfulPassesOppositionHalf": 333.0,
        "totalShots": 36.0,
        "unsuccessfulShortPasses": 231.0,
        "goalAssists": 3.0,
        "successfulLayoffs": 43.0,
        "unsuccessfulCrossesOpenPlay": 54.0,
        "goalKicks": 39.0,
        "cornersTakenInclShortCorners": 21.0,
        "aerialDuels": 156.0,
        "cleanSheets": 1.0,
        "shootingAccuracy": 41.67,
        "successfulCrossesAndCorners": 26.0,
        "unsuccessfulLayoffs": 4.0,
        "duelsWon": 254.0,
        "penaltiesConceded": 3.0,
        "putthroughBlockedDistribution": 74.0,
        "successfulShortPasses": 1687.0,
        "throwInsToOppositionPlayer": 14.0,
        "successfulOpenPlayPasses": 1707.0,
        "totalClearances": 121.0,
        "goalsConceded": 5.0,
        "groundDuelsLost": 176.0,
        "duels": 514.0,
        "putthroughBlockedDistributionWon": 28.0,
        "homeGoals": 5.0,
        "possessionPercentage": 51.1,
        "oboxTarget": 4.0,
        "tacklesLost": 44.0,
        "lastPlayerTackle": 2.0,
        "successfulPassesOppositionHalf": 850.0,
        "goalsConcededInsideBox": 5.0,
        "iboxBlocked": 7.0,
        "groundDuels": 358.0,
        "aerialDuelsWon": 72.0,
        "straightRedCards": 0.0,
        "cornersWon": 21.0,
        "successfulDribbles": 24.0,
        "blocks": 15.0,
        "gkUnsuccessfulDistribution": 13.0,
        "interceptions": 28.0,
        "unsuccessfulLaunches": 72.0,
        "foulAttemptedTackle": 33.0,
        "shotsOnConcededOutsideBox": 6.0,
        "goalConversion": 16.67,
        "expectedGoals": 5.3922,
        "yellowCards": 11.0
      }
    },
    {
      "teamMetadata": {
        "name": "Sunderland",
        "season": "2025",
        "id": "56",
        "shortName": "Sunderland",
        "abbr": "SUN"
      },
      "stats": {
        "duelsLost": 213.0,
        "penaltiesSaved": 1.0,
        "blockedShots": 15.0,
        "shotsOnTargetIncGoals": 13.0,
        "expectedGoalsOnTarget": 4.4059,
        "gamesPlayed": 5.0,
        "crossingAccuracy": 21.59,
        "totalPasses": 1962.0,
        "goals": 6.0,
        "offsides": 4.0,
        "awayGoals": 0.0,
        "tackleSuccess": 52.69,
        "oboxBlocked": 5.0,
        "passingAccuracy": 80.58,
        "iboxTarget": 5.0,
        "aerialDuelsLost": 87.0,
        "goalsConcededOutsideBox": 1.0,
        "groundDuelsWon": 159.0,
        "successfulCornersIntoBox": 6.0,
        "expectedGoalsOnTargetConceded": 4.9171,
        "keyPassesAttemptAssists": 31.0,
        "successfulLaunches": 23.0,
        "totalFoulsWon": 46.0,
        "recoveries": 191.0,
        "pointsGainedFromLosingPositions": 4.0,
        "passingPercentOppHalf": 71.62,
        "shotsOnConcededInsideBox": 14.0,
        "rightFootGoals": 3.0,
        "unsuccessfulDribbles": 23.0,
        "unsuccessfulCrossesAndCorners": 69.0,
        "timesTackled": 64.0,
        "openPlayPasses": 1859.0,
        "gkSuccessfulDistribution": 32.0,
        "shotsOffTargetIncWoodwork": 23.0,
        "totalLossesOfPossession": 601.0,
        "tacklesWon": 49.0,
        "totalShotsConceded": 52.0,
        "totalFoulsConceded": 46.0,
        "unsuccessfulCornersIntoBox": 12.0,
        "successfulLongPasses": 94.0,
        "clearancesOffTheLine": 1.0,
        "throwInsToOwnPlayer": 69.0,
        "touchesInOppBox": 81.0,
        "hitWoodwork": 1.0,
        "successfulPassesOwnHalf": 829.0,
        "handballsConceded": 3.0,
        "unsuccessfulLongPasses": 156.0,
        "unsuccessfulPassesOwnHalf": 83.0,
        "successfulCrossesOpenPlay": 14.0,
        "expectedAssists": 2.2437,
        "totalRedCards": 1.0,
        "catches": 6.0,
        "overruns": 8.0,
        "unsuccessfulPassesOppositionHalf": 367.0,
        "totalShots": 36.0,
        "unsuccessfulShortPasses": 225.0,
        "goalAssists": 4.0,
        "successfulLayoffs": 41.0,
        "foulWonPenalty": 1.0,
        "unsuccessfulCrossesOpenPlay": 53.0,
        "goalKicks": 39.0,
        "cornersTakenInclShortCorners": 20.0,
        "aerialDuels": 183.0,
        "cleanSheets": 2.0,
        "shootingAccuracy": 36.11,
        "successfulCrossesAndCorners": 19.0,
        "unsuccessfulLayoffs": 2.0,
        "duelsWon": 255.0,
        "penaltiesConceded": 1.0,
        "putthroughBlockedDistribution": 81.0,
        "successfulShortPasses": 1487.0,
        "throwInsToOppositionPlayer": 25.0,
        "successfulOpenPlayPasses": 1520.0,
        "totalClearances": 161.0,
        "goalsConceded": 4.0,
        "groundDuelsLost": 126.0,
        "duels": 468.0,
        "putthroughBlockedDistributionWon": 30.0,
        "homeGoals": 6.0,
        "possessionPercentage": 45.1,
        "oboxTarget": 2.0,
        "drops": 1.0,
        "tacklesLost": 44.0,
        "lastPlayerTackle": 1.0,
        "successfulPassesOppositionHalf": 771.0,
        "goalsConcededInsideBox": 3.0,
        "headedGoals": 3.0,
        "iboxBlocked": 10.0,
        "groundDuels": 285.0,
        "aerialDuelsWon": 96.0,
        "straightRedCards": 1.0,
        "cornersWon": 20.0,
        "successfulDribbles": 23.0,
        "blocks": 18.0,
        "gkUnsuccessfulDistribution": 21.0,
        "interceptions": 41.0,
        "penaltyGoals": 1.0,
        "unsuccessfulLaunches": 79.0,
        "foulAttemptedTackle": 22.0,
        "shotsOnConcededOutsideBox": 4.0,
        "goalConversion": 16.67,
        "expectedGoals": 4.4674,
        "yellowCards": 7.0
      }
    },
    {
      "teamMetadata": {
        "name": "Tottenham Hotspur",
        "season": "2025",
        "id": "6",
        "shortName": "Spurs",
        "abbr": "TOT"
      },
      "stats": {
        "duelsLost": 269.0,
        "blockedShots": 11.0,
        "shotsOnTargetIncGoals": 20.0,
        "expectedGoalsOnTarget": 8.6821,
        "gamesPlayed": 5.0,
        "crossingAccuracy": 20.66,
        "totalPasses": 2376.0,
        "goals": 10.0,
        "offsides": 8.0,
        "awayGoals": 7.0,
        "tackleSuccess": 57.45,
        "oboxBlocked": 5.0,
        "passingAccuracy": 85.56,
        "iboxTarget": 11.0,
        "aerialDuelsLost": 81.0,
        "goalsConcededOutsideBox": 1.0,
        "ownGoalsAccrued": 1.0,
        "groundDuelsWon": 192.0,
        "successfulCornersIntoBox": 7.0,
        "expectedGoalsOnTargetConceded": 4.7466,
        "keyPassesAttemptAssists": 35.0,
        "successfulLaunches": 15.0,
        "totalFoulsWon": 45.0,
        "recoveries": 246.0,
        "pointsGainedFromLosingPositions": 1.0,
        "passingPercentOppHalf": 78.62,
        "shotsOnConcededInsideBox": 15.0,
        "rightFootGoals": 7.0,
        "unsuccessfulDribbles": 57.0,
        "unsuccessfulCrossesAndCorners": 96.0,
        "timesTackled": 92.0,
        "freekickTotal": 1.0,
        "openPlayPasses": 2271.0,
        "gkSuccessfulDistribution": 65.0,
        "shotsOffTargetIncWoodwork": 27.0,
        "totalLossesOfPossession": 662.0,
        "tacklesWon": 54.0,
        "attemptsFromSetPieces": 1.0,
        "totalShotsConceded": 63.0,
        "totalFoulsConceded": 63.0,
        "unsuccessfulCornersIntoBox": 21.0,
        "successfulLongPasses": 109.0,
        "throwInsToOwnPlayer": 79.0,
        "touchesInOppBox": 151.0,
        "successfulPassesOwnHalf": 1099.0,
        "handballsConceded": 1.0,
        "unsuccessfulLongPasses": 131.0,
        "unsuccessfulPassesOwnHalf": 89.0,
        "successfulCrossesOpenPlay": 16.0,
        "expectedAssists": 3.7741,
        "totalRedCards": 0.0,
        "expectedGoalsFreekick": 0.054,
        "catches": 2.0,
        "overruns": 2.0,
        "unsuccessfulPassesOppositionHalf": 350.0,
        "totalShots": 47.0,
        "unsuccessfulShortPasses": 212.0,
        "goalAssists": 8.0,
        "successfulLayoffs": 30.0,
        "unsuccessfulCrossesOpenPlay": 74.0,
        "goalKicks": 45.0,
        "cornersTakenInclShortCorners": 31.0,
        "aerialDuels": 148.0,
        "cleanSheets": 3.0,
        "shootingAccuracy": 42.55,
        "successfulCrossesAndCorners": 25.0,
        "unsuccessfulLayoffs": 3.0,
        "duelsWon": 259.0,
        "putthroughBlockedDistribution": 73.0,
        "successfulShortPasses": 1924.0,
        "throwInsToOppositionPlayer": 22.0,
        "successfulOpenPlayPasses": 1939.0,
        "totalClearances": 111.0,
        "goalsConceded": 3.0,
        "groundDuelsLost": 188.0,
        "duels": 528.0,
        "putthroughBlockedDistributionWon": 32.0,
        "homeGoals": 3.0,
        "possessionPercentage": 58.5,
        "tacklesLost": 40.0,
        "lastPlayerTackle": 2.0,
        "successfulPassesOppositionHalf": 959.0,
        "goalsConcededInsideBox": 2.0,
        "headedGoals": 2.0,
        "iboxBlocked": 6.0,
        "groundDuels": 380.0,
        "aerialDuelsWon": 67.0,
        "straightRedCards": 0.0,
        "cornersWon": 31.0,
        "successfulDribbles": 53.0,
        "blocks": 11.0,
        "gkUnsuccessfulDistribution": 7.0,
        "interceptions": 24.0,
        "unsuccessfulLaunches": 59.0,
        "foulAttemptedTackle": 34.0,
        "shotsOnConcededOutsideBox": 7.0,
        "goalConversion": 21.28,
        "expectedGoals": 6.1311,
        "yellowCards": 9.0
      }
    },
    {
      "teamMetadata": {
        "name": "Aston Villa",
        "season": "2025",
        "id": "7",
        "shortName": "Aston Villa",
        "abbr": "AVL"
      },
      "stats": {
        "duelsLost": 266.0,
        "blockedShots": 20.0,
        "shotsOnTargetIncGoals": 12.0,
        "expectedGoalsOnTarget": 1.6305,
        "gamesPlayed": 5.0,
        "crossingAccuracy": 19.05,
        "totalPasses": 2359.0,
        "goals": 1.0,
        "offsides": 7.0,
        "awayGoals": 1.0,
        "tackleSuccess": 63.49,
        "oboxBlocked": 6.0,
        "passingAccuracy": 85.5,
        "iboxTarget": 7.0,
        "aerialDuelsLost": 80.0,
        "groundDuelsWon": 149.0,
        "successfulCornersIntoBox": 4.0,
        "penaltyGoalsConceded": 1.0,
        "expectedGoalsOnTargetConceded": 5.7292,
        "keyPassesAttemptAssists": 35.0,
        "successfulLaunches": 15.0,
        "totalFoulsWon": 64.0,
        "recoveries": 215.0,
        "passingPercentOppHalf": 82.15,
        "shotsOnConcededInsideBox": 11.0,
        "rightFootGoals": 1.0,
        "unsuccessfulDribbles": 51.0,
        "unsuccessfulCrossesAndCorners": 85.0,
        "timesTackled": 107.0,
        "freekickTotal": 1.0,
        "openPlayPasses": 2216.0,
        "gkSuccessfulDistribution": 57.0,
        "shotsOffTargetIncWoodwork": 20.0,
        "totalLossesOfPossession": 631.0,
        "tacklesWon": 40.0,
        "attemptsFromSetPieces": 1.0,
        "totalShotsConceded": 65.0,
        "totalFoulsConceded": 52.0,
        "unsuccessfulCornersIntoBox": 15.0,
        "successfulLongPasses": 100.0,
        "throwInsToOwnPlayer": 72.0,
        "touchesInOppBox": 119.0,
        "successfulPassesOwnHalf": 834.0,
        "pointsDroppedFromWinningPositions": 2.0,
        "unsuccessfulLongPasses": 126.0,
        "unsuccessfulPassesOwnHalf": 85.0,
        "successfulCrossesOpenPlay": 16.0,
        "expectedAssists": 3.6968,
        "totalRedCards": 1.0,
        "expectedGoalsFreekick": 0.0484,
        "catches": 5.0,
        "overruns": 4.0,
        "unsuccessfulPassesOppositionHalf": 342.0,
        "totalShots": 32.0,
        "unsuccessfulShortPasses": 216.0,
        "goalAssists": 1.0,
        "successfulLayoffs": 35.0,
        "unsuccessfulCrossesOpenPlay": 65.0,
        "goalKicks": 51.0,
        "cornersTakenInclShortCorners": 30.0,
        "aerialDuels": 151.0,
        "cleanSheets": 2.0,
        "shootingAccuracy": 37.5,
        "successfulCrossesAndCorners": 20.0,
        "unsuccessfulLayoffs": 4.0,
        "duelsWon": 220.0,
        "penaltiesConceded": 1.0,
        "putthroughBlockedDistribution": 79.0,
        "successfulShortPasses": 1917.0,
        "throwInsToOppositionPlayer": 21.0,
        "successfulOpenPlayPasses": 1900.0,
        "totalClearances": 96.0,
        "goalsConceded": 5.0,
        "groundDuelsLost": 186.0,
        "duels": 486.0,
        "putthroughBlockedDistributionWon": 28.0,
        "homeGoals": 0.0,
        "possessionPercentage": 59.5,
        "oboxTarget": 4.0,
        "drops": 1.0,
        "tacklesLost": 23.0,
        "successfulPassesOppositionHalf": 1203.0,
        "goalsConcededInsideBox": 5.0,
        "iboxBlocked": 14.0,
        "groundDuels": 335.0,
        "aerialDuelsWon": 71.0,
        "straightRedCards": 1.0,
        "cornersWon": 30.0,
        "successfulDribbles": 26.0,
        "blocks": 24.0,
        "gkUnsuccessfulDistribution": 13.0,
        "interceptions": 29.0,
        "unsuccessfulLaunches": 54.0,
        "foulAttemptedTackle": 25.0,
        "shotsOnConcededOutsideBox": 4.0,
        "goalConversion": 3.12,
        "expectedGoals": 3.8538,
        "yellowCards": 9.0
      }
    },
    {
      "teamMetadata": {
        "name": "Chelsea",
        "season": "2025",
        "id": "8",
        "shortName": "Chelsea",
        "abbr": "CHE"
      },
      "stats": {
        "duelsLost": 237.0,
        "blockedShots": 25.0,
        "shotsOnTargetIncGoals": 23.0,
        "expectedGoalsOnTarget": 11.8044,
        "gamesPlayed": 5.0,
        "crossingAccuracy": 20.22,
        "totalPasses": 2759.0,
        "goals": 10.0,
        "offsides": 11.0,
        "awayGoals": 8.0,
        "tackleSuccess": 60.98,
        "oboxBlocked": 11.0,
        "passingAccuracy": 87.93,
        "iboxTarget": 10.0,
        "aerialDuelsLost": 62.0,
        "goalsConcededOutsideBox": 1.0,
        "groundDuelsWon": 177.0,
        "successfulCornersIntoBox": 9.0,
        "expectedGoalsOnTargetConceded": 4.8563,
        "keyPassesAttemptAssists": 38.0,
        "successfulLaunches": 19.0,
        "totalFoulsWon": 59.0,
        "recoveries": 210.0,
        "pointsGainedFromLosingPositions": 4.0,
        "passingPercentOppHalf": 83.5,
        "shotsOnConcededInsideBox": 12.0,
        "rightFootGoals": 4.0,
        "leftFootGoals": 3.0,
        "unsuccessfulDribbles": 43.0,
        "unsuccessfulCrossesAndCorners": 71.0,
        "timesTackled": 94.0,
        "freekickTotal": 2.0,
        "openPlayPasses": 2645.0,
        "gkSuccessfulDistribution": 41.0,
        "shotsOffTargetIncWoodwork": 17.0,
        "totalLossesOfPossession": 595.0,
        "tacklesWon": 50.0,
        "attemptsFromSetPieces": 2.0,
        "totalShotsConceded": 52.0,
        "totalFoulsConceded": 54.0,
        "unsuccessfulCornersIntoBox": 15.0,
        "successfulLongPasses": 99.0,
        "clearancesOffTheLine": 1.0,
        "throwInsToOwnPlayer": 87.0,
        "touchesInOppBox": 138.0,
        "hitWoodwork": 1.0,
        "successfulPassesOwnHalf": 1232.0,
        "pointsDroppedFromWinningPositions": 2.0,
        "handballsConceded": 1.0,
        "unsuccessfulLongPasses": 126.0,
        "unsuccessfulPassesOwnHalf": 97.0,
        "successfulCrossesOpenPlay": 9.0,
        "expectedAssists": 5.0149,
        "totalRedCards": 1.0,
        "expectedGoalsFreekick": 0.0772,
        "catches": 4.0,
        "overruns": 3.0,
        "unsuccessfulPassesOppositionHalf": 307.0,
        "totalShots": 40.0,
        "unsuccessfulShortPasses": 207.0,
        "goalAssists": 7.0,
        "successfulLayoffs": 63.0,
        "foulWonPenalty": 1.0,
        "unsuccessfulCrossesOpenPlay": 53.0,
        "goalKicks": 29.0,
        "cornersTakenInclShortCorners": 33.0,
        "aerialDuels": 141.0,
        "cleanSheets": 2.0,
        "shootingAccuracy": 57.5,
        "successfulCrossesAndCorners": 18.0,
        "unsuccessfulLayoffs": 3.0,
        "duelsWon": 256.0,
        "putthroughBlockedDistribution": 57.0,
        "successfulShortPasses": 2327.0,
        "throwInsToOppositionPlayer": 6.0,
        "successfulOpenPlayPasses": 2321.0,
        "totalClearances": 118.0,
        "goalsConceded": 5.0,
        "groundDuelsLost": 175.0,
        "duels": 493.0,
        "putthroughBlockedDistributionWon": 23.0,
        "homeGoals": 2.0,
        "possessionPercentage": 61.3,
        "oboxTarget": 3.0,
        "tacklesLost": 32.0,
        "lastPlayerTackle": 1.0,
        "successfulPassesOppositionHalf": 1212.0,
        "goalsConcededInsideBox": 4.0,
        "headedGoals": 3.0,
        "iboxBlocked": 14.0,
        "groundDuels": 352.0,
        "aerialDuelsWon": 79.0,
        "straightRedCards": 1.0,
        "cornersWon": 33.0,
        "successfulDribbles": 36.0,
        "blocks": 14.0,
        "gkUnsuccessfulDistribution": 5.0,
        "interceptions": 54.0,
        "penaltyGoals": 1.0,
        "unsuccessfulLaunches": 56.0,
        "foulAttemptedTackle": 31.0,
        "shotsOnConcededOutsideBox": 7.0,
        "goalConversion": 25.0,
        "expectedGoals": 8.375,
        "yellowCards": 12.0
      }
    },
    {
      "teamMetadata": {
        "name": "Burnley",
        "season": "2025",
        "id": "90",
        "shortName": "Burnley",
        "abbr": "BUR"
      },
      "stats": {
        "duelsLost": 238.0,
        "blockedShots": 9.0,
        "shotsOnTargetIncGoals": 14.0,
        "expectedGoalsOnTarget": 5.289,
        "gamesPlayed": 5.0,
        "crossingAccuracy": 23.88,
        "totalPasses": 1522.0,
        "goals": 5.0,
        "offsides": 9.0,
        "awayGoals": 2.0,
        "tackleSuccess": 62.67,
        "redCard2ndYellow": 1.0,
        "oboxBlocked": 4.0,
        "passingAccuracy": 73.0,
        "iboxTarget": 5.0,
        "aerialDuelsLost": 95.0,
        "groundDuelsWon": 144.0,
        "successfulCornersIntoBox": 2.0,
        "penaltyGoalsConceded": 2.0,
        "expectedGoalsOnTargetConceded": 8.1313,
        "keyPassesAttemptAssists": 28.0,
        "successfulLaunches": 24.0,
        "totalFoulsWon": 45.0,
        "recoveries": 207.0,
        "pointsGainedFromLosingPositions": 1.0,
        "passingPercentOppHalf": 63.53,
        "shotsOnConcededInsideBox": 22.0,
        "rightFootGoals": 2.0,
        "leftFootGoals": 3.0,
        "unsuccessfulDribbles": 25.0,
        "unsuccessfulCrossesAndCorners": 51.0,
        "timesTackled": 67.0,
        "freekickTotal": 3.0,
        "openPlayPasses": 1390.0,
        "gkSuccessfulDistribution": 46.0,
        "shotsOffTargetIncWoodwork": 19.0,
        "totalLossesOfPossession": 632.0,
        "tacklesWon": 47.0,
        "attemptsFromSetPieces": 3.0,
        "totalShotsConceded": 95.0,
        "totalFoulsConceded": 47.0,
        "unsuccessfulCornersIntoBox": 11.0,
        "successfulLongPasses": 88.0,
        "throwInsToOwnPlayer": 38.0,
        "touchesInOppBox": 85.0,
        "hitWoodwork": 2.0,
        "successfulPassesOwnHalf": 543.0,
        "ownGoalsConceded": 1.0,
        "handballsConceded": 3.0,
        "unsuccessfulLongPasses": 189.0,
        "unsuccessfulPassesOwnHalf": 85.0,
        "successfulCrossesOpenPlay": 13.0,
        "expectedAssists": 2.7713,
        "totalRedCards": 1.0,
        "expectedGoalsFreekick": 0.1067,
        "catches": 6.0,
        "overruns": 7.0,
        "unsuccessfulPassesOppositionHalf": 377.0,
        "totalShots": 33.0,
        "unsuccessfulShortPasses": 222.0,
        "goalAssists": 4.0,
        "successfulLayoffs": 27.0,
        "unsuccessfulCrossesOpenPlay": 35.0,
        "goalKicks": 67.0,
        "cornersTakenInclShortCorners": 15.0,
        "aerialDuels": 180.0,
        "cleanSheets": 1.0,
        "shootingAccuracy": 42.42,
        "successfulCrossesAndCorners": 16.0,
        "unsuccessfulLayoffs": 2.0,
        "duelsWon": 229.0,
        "penaltiesConceded": 2.0,
        "putthroughBlockedDistribution": 87.0,
        "successfulShortPasses": 1023.0,
        "throwInsToOppositionPlayer": 29.0,
        "successfulOpenPlayPasses": 1057.0,
        "totalClearances": 176.0,
        "goalsConceded": 8.0,
        "groundDuelsLost": 143.0,
        "duels": 467.0,
        "putthroughBlockedDistributionWon": 40.0,
        "homeGoals": 3.0,
        "possessionPercentage": 34.8,
        "oboxTarget": 4.0,
        "tacklesLost": 28.0,
        "lastPlayerTackle": 1.0,
        "successfulPassesOppositionHalf": 584.0,
        "goalsConcededInsideBox": 8.0,
        "iboxBlocked": 5.0,
        "groundDuels": 287.0,
        "aerialDuelsWon": 85.0,
        "straightRedCards": 0.0,
        "cornersWon": 15.0,
        "successfulDribbles": 26.0,
        "blocks": 31.0,
        "gkUnsuccessfulDistribution": 49.0,
        "interceptions": 50.0,
        "unsuccessfulLaunches": 84.0,
        "foulAttemptedTackle": 24.0,
        "shotsOnConcededOutsideBox": 4.0,
        "goalConversion": 15.15,
        "expectedGoals": 4.1224,
        "yellowCards": 6.0
      }
    },
    {
      "teamMetadata": {
        "name": "Bournemouth",
        "season": "2025",
        "id": "91",
        "shortName": "Bournemouth",
        "abbr": "BOU"
      },
      "stats": {
        "duelsLost": 292.0,
        "blockedShots": 23.0,
        "shotsOnTargetIncGoals": 20.0,
        "expectedGoalsOnTarget": 4.9811,
        "gamesPlayed": 5.0,
        "crossingAccuracy": 17.35,
        "totalPasses": 1933.0,
        "goals": 6.0,
        "offsides": 11.0,
        "awayGoals": 3.0,
        "tackleSuccess": 60.22,
        "oboxBlocked": 10.0,
        "passingAccuracy": 78.74,
        "iboxTarget": 9.0,
        "aerialDuelsLost": 96.0,
        "groundDuelsWon": 186.0,
        "successfulCornersIntoBox": 3.0,
        "expectedGoalsOnTargetConceded": 4.8735,
        "keyPassesAttemptAssists": 44.0,
        "successfulLaunches": 19.0,
        "totalFoulsWon": 57.0,
        "recoveries": 255.0,
        "passingPercentOppHalf": 69.9,
        "shotsOnConcededInsideBox": 13.0,
        "rightFootGoals": 1.0,
        "leftFootGoals": 5.0,
        "unsuccessfulDribbles": 50.0,
        "unsuccessfulCrossesAndCorners": 81.0,
        "timesTackled": 92.0,
        "freekickTotal": 7.0,
        "openPlayPasses": 1817.0,
        "gkSuccessfulDistribution": 44.0,
        "shotsOffTargetIncWoodwork": 25.0,
        "totalLossesOfPossession": 705.0,
        "tacklesWon": 56.0,
        "attemptsFromSetPieces": 7.0,
        "totalShotsConceded": 40.0,
        "totalFoulsConceded": 59.0,
        "unsuccessfulCornersIntoBox": 25.0,
        "successfulLongPasses": 108.0,
        "throwInsToOwnPlayer": 60.0,
        "touchesInOppBox": 131.0,
        "hitWoodwork": 2.0,
        "successfulPassesOwnHalf": 758.0,
        "unsuccessfulLongPasses": 187.0,
        "unsuccessfulPassesOwnHalf": 82.0,
        "successfulCrossesOpenPlay": 14.0,
        "expectedAssists": 3.7914,
        "totalRedCards": 0.0,
        "expectedGoalsFreekick": 0.4613,
        "catches": 7.0,
        "overruns": 4.0,
        "unsuccessfulPassesOppositionHalf": 410.0,
        "totalShots": 45.0,
        "unsuccessfulShortPasses": 224.0,
        "goalAssists": 5.0,
        "successfulLayoffs": 26.0,
        "foulWonPenalty": 1.0,
        "unsuccessfulCrossesOpenPlay": 53.0,
        "goalKicks": 44.0,
        "cornersTakenInclShortCorners": 32.0,
        "aerialDuels": 174.0,
        "cleanSheets": 3.0,
        "shootingAccuracy": 44.44,
        "successfulCrossesAndCorners": 17.0,
        "unsuccessfulLayoffs": 1.0,
        "duelsWon": 264.0,
        "putthroughBlockedDistribution": 97.0,
        "successfulShortPasses": 1414.0,
        "throwInsToOppositionPlayer": 34.0,
        "successfulOpenPlayPasses": 1441.0,
        "totalClearances": 171.0,
        "goalsConceded": 5.0,
        "groundDuelsLost": 196.0,
        "duels": 556.0,
        "putthroughBlockedDistributionWon": 47.0,
        "homeGoals": 3.0,
        "possessionPercentage": 49.0,
        "oboxTarget": 5.0,
        "tacklesLost": 37.0,
        "successfulPassesOppositionHalf": 781.0,
        "goalsConcededInsideBox": 5.0,
        "iboxBlocked": 13.0,
        "groundDuels": 382.0,
        "aerialDuelsWon": 78.0,
        "straightRedCards": 0.0,
        "cornersWon": 32.0,
        "successfulDribbles": 38.0,
        "blocks": 7.0,
        "gkUnsuccessfulDistribution": 19.0,
        "interceptions": 45.0,
        "penaltyGoals": 1.0,
        "unsuccessfulLaunches": 89.0,
        "foulAttemptedTackle": 30.0,
        "shotsOnConcededOutsideBox": 2.0,
        "goalConversion": 13.33,
        "expectedGoals": 6.4853,
        "yellowCards": 14.0
      }
    },
    {
      "teamMetadata": {
        "name": "Brentford",
        "season": "2025",
        "id": "94",
        "shortName": "Brentford",
        "abbr": "BRE"
      },
      "stats": {
        "duelsLost": 270.0,
        "blockedShots": 11.0,
        "shotsOnTargetIncGoals": 16.0,
        "expectedGoalsOnTarget": 7.4607,
        "gamesPlayed": 5.0,
        "crossingAccuracy": 26.83,
        "totalPasses": 1560.0,
        "goals": 6.0,
        "offsides": 6.0,
        "awayGoals": 3.0,
        "tackleSuccess": 50.57,
        "oboxBlocked": 1.0,
        "passingAccuracy": 78.27,
        "iboxTarget": 8.0,
        "aerialDuelsLost": 94.0,
        "goalsConcededOutsideBox": 1.0,
        "groundDuelsWon": 167.0,
        "successfulCornersIntoBox": 7.0,
        "penaltyGoalsConceded": 1.0,
        "expectedGoalsOnTargetConceded": 6.7248,
        "keyPassesAttemptAssists": 24.0,
        "successfulLaunches": 30.0,
        "totalFoulsWon": 43.0,
        "recoveries": 218.0,
        "pointsGainedFromLosingPositions": 1.0,
        "passingPercentOppHalf": 62.89,
        "shotsOnConcededInsideBox": 14.0,
        "rightFootGoals": 4.0,
        "leftFootGoals": 1.0,
        "unsuccessfulDribbles": 46.0,
        "unsuccessfulCrossesAndCorners": 60.0,
        "timesTackled": 88.0,
        "openPlayPasses": 1451.0,
        "gkSuccessfulDistribution": 44.0,
        "shotsOffTargetIncWoodwork": 14.0,
        "totalLossesOfPossession": 613.0,
        "tacklesWon": 44.0,
        "totalShotsConceded": 70.0,
        "totalFoulsConceded": 64.0,
        "unsuccessfulCornersIntoBox": 15.0,
        "successfulLongPasses": 99.0,
        "throwInsToOwnPlayer": 46.0,
        "touchesInOppBox": 95.0,
        "successfulPassesOwnHalf": 777.0,
        "pointsDroppedFromWinningPositions": 8.0,
        "ownGoalsConceded": 1.0,
        "handballsConceded": 2.0,
        "unsuccessfulLongPasses": 135.0,
        "unsuccessfulPassesOwnHalf": 77.0,
        "successfulCrossesOpenPlay": 14.0,
        "expectedAssists": 2.6116,
        "totalRedCards": 0.0,
        "catches": 1.0,
        "overruns": 3.0,
        "unsuccessfulPassesOppositionHalf": 322.0,
        "totalShots": 30.0,
        "unsuccessfulShortPasses": 204.0,
        "goalAssists": 3.0,
        "successfulLayoffs": 19.0,
        "foulWonPenalty": 2.0,
        "unsuccessfulCrossesOpenPlay": 41.0,
        "goalKicks": 38.0,
        "cornersTakenInclShortCorners": 26.0,
        "aerialDuels": 166.0,
        "cleanSheets": 1.0,
        "shootingAccuracy": 53.33,
        "successfulCrossesAndCorners": 22.0,
        "unsuccessfulLayoffs": 1.0,
        "duelsWon": 239.0,
        "penaltiesConceded": 1.0,
        "putthroughBlockedDistribution": 68.0,
        "successfulShortPasses": 1122.0,
        "throwInsToOppositionPlayer": 40.0,
        "successfulOpenPlayPasses": 1151.0,
        "totalClearances": 157.0,
        "goalsConceded": 10.0,
        "groundDuelsLost": 176.0,
        "duels": 509.0,
        "putthroughBlockedDistributionWon": 43.0,
        "homeGoals": 3.0,
        "possessionPercentage": 39.6,
        "oboxTarget": 2.0,
        "drops": 1.0,
        "tacklesLost": 43.0,
        "lastPlayerTackle": 1.0,
        "successfulPassesOppositionHalf": 466.0,
        "goalsConcededInsideBox": 9.0,
        "headedGoals": 1.0,
        "iboxBlocked": 10.0,
        "groundDuels": 343.0,
        "aerialDuelsWon": 72.0,
        "straightRedCards": 0.0,
        "cornersWon": 26.0,
        "successfulDribbles": 38.0,
        "blocks": 25.0,
        "gkUnsuccessfulDistribution": 19.0,
        "interceptions": 31.0,
        "penaltyGoals": 1.0,
        "unsuccessfulLaunches": 74.0,
        "foulAttemptedTackle": 25.0,
        "shotsOnConcededOutsideBox": 6.0,
        "goalConversion": 20.0,
        "expectedGoals": 5.9316,
        "yellowCards": 9.0
      }
    }
  ]
}
